{
  "generated_at_utc": "2026-06-17T03:44:40Z",
  "date": "2026-06-17",
  "item_count": 75,
  "errors": [
    {
      "provider": "jikan_season_now",
      "error": "504 Server Error: Gateway Time-out for url: https://api.jikan.moe/v4/seasons/now?limit=15"
    },
    {
      "provider": "jikan_top_manga",
      "error": "504 Server Error: Gateway Time-out for url: https://api.jikan.moe/v4/top/manga?limit=15"
    },
    {
      "provider": "jikan_top_novels",
      "error": "504 Server Error: Gateway Time-out for url: https://api.jikan.moe/v4/top/manga?limit=15&type=lightnovels"
    },
    {
      "provider": "reddit_discussed",
      "error": "403 Client Error: Blocked for url: https://www.reddit.com/r/manhwa/hot.json?limit=15"
    }
  ],
  "items": [
    {
      "id": "webnovel-book-gacha-harem-system_35385385708000905",
      "title": "Gacha Harem System",
      "source": "WebNovel",
      "category": "web_novel",
      "score": 4.0,
      "url": "https://www.webnovel.com/book/gacha-harem-system_35385385708000905",
      "image": "https://book-pic.webnovel.com/bookcover/35385385708000905?imageMogr2/thumbnail/600x&imageId=1781541166055",
      "description": "# ACTION # ROMANCE # ADVENTURE # SYSTEM # R18 # COMEDY # HAREM # OVERPOWERED # TRANSMIGRATION # SLICEOFLIFE",
      "genres": [
        "Web Novel"
      ],
      "metadata": {
        "ranking_page": "https://www.webnovel.com/ranking/novel/season/best_sellers"
      },
      "previous_score": 2.0,
      "velocity": 1.0
    },
    {
      "id": "webnovel-book-last-born-of-the-desdemona_35438027108926505",
      "title": "Last Born Of The Desdemona",
      "source": "WebNovel",
      "category": "web_novel",
      "score": 12.0,
      "url": "https://www.webnovel.com/book/last-born-of-the-desdemona_35438027108926505",
      "image": "https://book-pic.webnovel.com/bookcover/35438027108926505?imageMogr2/thumbnail/600x&imageId=1774464813616",
      "description": "# ACTION # ROMANCE # ADVENTURE # SYSTEM # REINCARNATION # R18 # OVERPOWERED # VILLAIN # EVOLUTION # YANDERE",
      "genres": [
        "Web Novel"
      ],
      "metadata": {
        "ranking_page": "https://www.webnovel.com/ranking/novel/season/best_sellers"
      },
      "previous_score": 7.0,
      "velocity": 0.7142857142857143
    },
    {
      "id": "goodnovel-book-The-Mafia-King-s-Unknown-Doctor-Wife_31001049746",
      "title": "The Mafia King's Unknown Doctor Wife",
      "source": "GoodNovel",
      "category": "romance",
      "score": 15.0,
      "url": "https://www.goodnovel.com/book/The-Mafia-King-s-Unknown-Doctor-Wife_31001049746",
      "image": "https://acf.goodnovel.com/book/202601/506a769afc2aa4309a9d731abc9510e50597d7b41fd77754529b43da1a523af5.jpg?v=1&p=1&w=1080&a=webp",
      "description": "Elena, the daughter of a notorious mafia family, was offered as a tribute to the leader of the Morello family by her father. In an attempt to escape an arranged marriage, Elena marries a complete stranger. What she doesn't know is that this mysterious husband of hers is none other than the legendary mafia king... and now, he’s also her new boss...",
      "genres": [
        "Romance"
      ],
      "metadata": {
        "ranking_page": "https://www.goodnovel.com/"
      },
      "previous_score": 11.0,
      "velocity": 0.36363636363636365
    },
    {
      "id": "webnovel-book-working-in-a-zoo-with-beast-taming-system_35475348608544705",
      "title": "Working in a Zoo with Beast Taming System",
      "source": "WebNovel",
      "category": "web_novel",
      "score": 10.0,
      "url": "https://www.webnovel.com/book/working-in-a-zoo-with-beast-taming-system_35475348608544705",
      "image": "https://book-pic.webnovel.com/bookcover/35475348608544705?imageMogr2/thumbnail/600x&imageId=1778641179571",
      "description": "# SYSTEM # BEAST TAMING",
      "genres": [
        "Web Novel"
      ],
      "metadata": {
        "ranking_page": "https://www.webnovel.com/ranking/novel/season/best_sellers"
      },
      "previous_score": 8.0,
      "velocity": 0.25
    },
    {
      "id": "webnovel-book-infinite-cashback-system_35674644400458505",
      "title": "Infinite Cashback System",
      "source": "WebNovel",
      "category": "web_novel",
      "score": 6.0,
      "url": "https://www.webnovel.com/book/infinite-cashback-system_35674644400458505",
      "image": "https://book-pic.webnovel.com/bookcover/35674644400458505?imageMogr2/thumbnail/600x&imageId=1780250189855",
      "description": "# ROMANCE # ADVENTURE # R18 # HAREM # SLICEOFLIFE # CAMPUS # ACADEMY # URBAN # CEO # POORTORICH",
      "genres": [
        "Web Novel"
      ],
      "metadata": {
        "ranking_page": "https://www.webnovel.com/ranking/novel/season/best_sellers"
      },
      "previous_score": 5.0,
      "velocity": 0.2
    },
    {
      "id": "anilist-anime-189987",
      "title": "The Klutzy Class Monitor and the Girl with the Short Skirt",
      "source": "AniList",
      "category": "anime",
      "score": 29321.0,
      "url": "https://anilist.co/anime/189987",
      "image": "https://s4.anilist.co/file/anilistcdn/media/anime/cover/large/bx189987-CkTDPfD7vu2Y.jpg",
      "description": "Sakuradaimon is the school's prefect. A prefect is a student who is authorized to enforce discipline. As a prefect, he's supposed to be a role model to other students, but unfortunately he's not perfect. Kohinata is one of the people who Sakuradaimon has tried to discipline into wearing appropriate school attire, but she has thusfar been disobedient.<br>\n<br>\nAnd so this is a story of the two interacting with one another.",
      "genres": [
        "Comedy",
        "Romance",
        "Slice of Life"
      ],
      "metadata": {
        "average_score": 75
      },
      "previous_score": 28986.0,
      "velocity": 0.01155730352584006
    },
    {
      "id": "anilist-anime-206914",
      "title": "NIPPON SANGOKU: The Three Nations of the Crimson Sun",
      "source": "AniList",
      "category": "anime",
      "score": 43247.0,
      "url": "https://anilist.co/anime/206914",
      "image": "https://s4.anilist.co/file/anilistcdn/media/anime/cover/large/bx206914-SHKX08LarRzB.jpg",
      "description": "A revolution sparked by nuclear war, natural disaster, and misrule leads to the collapse of Japanese society. The country splits into three nations vying for hegemony, and the Sangoku era begins. Aoteru Misumi, a former agricultural officer, vows to reunify Japan. He rises through the ranks with only his knowledge and eloquence. Witness the legend of the man later hailed as a genius strategist.\n<br><br>\n(Source: Amazon Prime Video)",
      "genres": [
        "Action",
        "Drama",
        "Sci-Fi"
      ],
      "metadata": {
        "average_score": 82
      },
      "previous_score": 42869.0,
      "velocity": 0.008817560474935269
    },
    {
      "id": "anilist-anime-197824",
      "title": "Farming Life in Another World 2",
      "source": "AniList",
      "category": "anime",
      "score": 42048.0,
      "url": "https://anilist.co/anime/197824",
      "image": "https://s4.anilist.co/file/anilistcdn/media/anime/cover/large/bx197824-k9Uyef8g49hB.png",
      "description": "The second season of <i>Isekai Nonbiri Nouka</i>.\n<br><br>\n\n<i>Note: World premiere of Episode 1 before the Japanese television premiere occurred at ANIMONIUM in Bangkok February 8, 2026</i>",
      "genres": [
        "Fantasy",
        "Slice of Life"
      ],
      "metadata": {
        "average_score": 73
      },
      "previous_score": 41740.0,
      "velocity": 0.0073790129372304746
    },
    {
      "id": "anilist-anime-182300",
      "title": "Wistoria: Wand and Sword Season 2",
      "source": "AniList",
      "category": "anime",
      "score": 92559.0,
      "url": "https://anilist.co/anime/182300",
      "image": "https://s4.anilist.co/file/anilistcdn/media/anime/cover/large/bx182300-IYkq5KrkQq1V.jpg",
      "description": "The second season of <i>Tsue to Tsurugi no Wistoria</i>.<br><br>\nWill, a washout student at a magical academy who is unable to use magic, is aiming to join the top tier of mages, the Magia Vander, to fulfill a promise to his childhood friend, Elfaria. Wielding a sword instead of a wand, his abilities are slowly recognized within the academy. During the all-student praxis dungeon training he undertakes with Lihanna and the other top students of his year, they are ambushed by a mysterious mage. Though they barely manage to survive the attack together, they go on to face the exit exam. Can Will reach the girl waiting for him in the tower?<br><br>\n(Source: Official Site)",
      "genres": [
        "Action",
        "Adventure",
        "Drama",
        "Fantasy"
      ],
      "metadata": {
        "average_score": 82
      },
      "previous_score": 91942.0,
      "velocity": 0.006710752430880338
    },
    {
      "id": "anilist-anime-147105",
      "title": "Witch Hat Atelier",
      "source": "AniList",
      "category": "anime",
      "score": 178167.0,
      "url": "https://anilist.co/anime/147105",
      "image": "https://s4.anilist.co/file/anilistcdn/media/anime/cover/large/bx147105-rwOX8qyUy8gV.jpg",
      "description": "In a world where everyone takes wonders like magic spells and dragons for granted, Coco is a girl with a simple dream: she wants to be a witch. But everybody knows magicians are born, not made, and Coco was not born with a gift for magic. Resigned to her un-magical life, Coco is about to give up on her dream to become a witch … until the day she meets Qifrey, a mysterious, traveling magician. After secretly seeing Qifrey perform magic in a way she’s never seen before, Coco soon learns what everybody “knows” might not be the truth, and discovers that her magical dream may not be as far away as it may seem... <br>\n<br>\n(Source: Kodansha USA) <br><br>\n\n<i>Note: Tongari Boushi no Atelier episode 2 was streamed a week in advance on Crunchyroll, ABEMA, and Netflix, alongside episode 1. Streaming is one week ahead of the TV broadcast.</i>",
      "genres": [
        "Adventure",
        "Drama",
        "Fantasy"
      ],
      "metadata": {
        "average_score": 86
      },
      "previous_score": 177111.0,
      "velocity": 0.005962362586174772
    },
    {
      "id": "anilist-manga-183376",
      "title": "Chronicles of a Doomed Prodigy",
      "source": "AniList",
      "category": "manhwa",
      "score": 6984.0,
      "url": "https://anilist.co/manga/183376",
      "image": "https://s4.anilist.co/file/anilistcdn/media/manga/cover/large/bx183376-Cw3VnZAItw2a.jpg",
      "description": "Gifted by the heavens yet cursed by fate, Yeonshin was born with unimaginable talent in martial arts. But this very gift condemned him to a life that would end before adulthood. With the right opportunities, he had the potential to become a legendary hero, or the reincarnation of the Heavenly Demon. Yet fate cast him into the third-rate Jeong Clan, a family of no particular renown. Now, with time slipping through his fingers, Yeonshin must find a way to defy his doomed destiny.<br><br>(Source: WEBTOON)",
      "genres": [
        "Action",
        "Adventure",
        "Fantasy"
      ],
      "metadata": {
        "average_score": 75,
        "country_of_origin": "KR",
        "format": "MANGA"
      },
      "previous_score": 6952.0,
      "velocity": 0.004602991944764097
    },
    {
      "id": "anilist-anime-195600",
      "title": "Daemons of the Shadow Realm",
      "source": "AniList",
      "category": "anime",
      "score": 104096.0,
      "url": "https://anilist.co/anime/195600",
      "image": "https://s4.anilist.co/file/anilistcdn/media/anime/cover/large/bx195600-moI0UFArtOme.jpg",
      "description": "In a remote mountain village under the watchful eyes of two stone guardians, the young Yuru contentedly lives off the land while staying close to the only family he has left—Asa, his precious twin sister. Asa, meanwhile, carries out a mysterious “duty” on behalf of the village while locked in a cage. Why is Asa a prisoner? And what other secrets does Yuru’s otherwise idyllic home hide?\n<br><br>(Source: Square Enix)",
      "genres": [
        "Action",
        "Adventure",
        "Comedy",
        "Fantasy",
        "Supernatural"
      ],
      "metadata": {
        "average_score": 78
      },
      "previous_score": 103705.0,
      "velocity": 0.003770310013981968
    },
    {
      "id": "anilist-anime-189046",
      "title": "Re:ZERO -Starting Life in Another World- Season 4",
      "source": "AniList",
      "category": "anime",
      "score": 108302.0,
      "url": "https://anilist.co/anime/189046",
      "image": "https://s4.anilist.co/file/anilistcdn/media/anime/cover/large/bx189046-yaHWtS5FII46.jpg",
      "description": "The fourth season of <i>Re:Zero kara Hajimeru Isekai Seikatsu</i>.<br><br>\n\nTo save his stricken allies, Subaru faces a deadly desert to find the Sage at Pleiades Watchtower.<br><br>\n\n(Source: Crunchyroll News)\n\n<br><br>\n<i>Note: Episode 1 pre-screened at Lucca Comics & Games on November 1, 2025, before the Japanese television broadcast.",
      "genres": [
        "Action",
        "Adventure",
        "Drama",
        "Fantasy",
        "Psychological",
        "Romance",
        "Thriller"
      ],
      "metadata": {
        "average_score": 88
      },
      "previous_score": 107897.0,
      "velocity": 0.003753579802960231
    },
    {
      "id": "anilist-anime-182205",
      "title": "That Time I Got Reincarnated as a Slime Season 4",
      "source": "AniList",
      "category": "anime",
      "score": 101491.0,
      "url": "https://anilist.co/anime/182205",
      "image": "https://s4.anilist.co/file/anilistcdn/media/anime/cover/large/bx182205-q2AeO1owuQbO.jpg",
      "description": "The fourth season of <i>Tensei Shitara Slime Datta Ken</i>.<br><br>\nDemon Lord Rimuru's dream of creating an alliance between humans and monsters takes a step closer to being realized. As Tempest continues to prosper, Granville Rozzo and his granddaughter, Maribel Rozzo, clash with Demon Lord Rimuru over their plan to protect mankind by ruling over them. Meanwhile, in El Dorado, Demon Lord Leon works toward goals of his own. The awakening of a new Hero draws near!<br><br>\n\n(Source: Crunchyroll News)",
      "genres": [
        "Action",
        "Adventure",
        "Comedy",
        "Fantasy"
      ],
      "metadata": {
        "average_score": 81
      },
      "previous_score": 101114.0,
      "velocity": 0.0037284649010028287
    },
    {
      "id": "anilist-anime-180745",
      "title": "Classroom of the Elite 4th Season: Second Year, First Semester",
      "source": "AniList",
      "category": "anime",
      "score": 97896.0,
      "url": "https://anilist.co/anime/180745",
      "image": "https://s4.anilist.co/file/anilistcdn/media/anime/cover/large/bx180745-OEZaBeEdWozn.png",
      "description": "The fourth season of <i> Youkoso Jitsuryoku Shijou Shugi no Kyoushitsu e</i>.<br><br>\nAs Ayanokouji and his classmates begin their second year at the Advanced Nurturing High School, they’re greeted by a fresh gauntlet of exams and a fresh batch of rather unique first-year students. They’ll have to get to know each other quickly, because the first special exam pairs the first-years with the second-years on a written test—with only the second-years facing expulsion if their team performs poorly! Worse yet? It seems one of the new first-years is also from the White Room. Can Ayanokouji avoid expulsion while sussing out the identity of this hidden foe?\n<br><br>\n(Source: Seven Seas)",
      "genres": [
        "Drama",
        "Psychological"
      ],
      "metadata": {
        "average_score": 78
      },
      "previous_score": 97605.0,
      "velocity": 0.0029814046411556785
    },
    {
      "id": "anilist-manga-182066",
      "title": "The Regressed Mercenary Has a Plan",
      "source": "AniList",
      "category": "manhwa",
      "score": 20359.0,
      "url": "https://anilist.co/manga/182066",
      "image": "https://s4.anilist.co/file/anilistcdn/media/manga/cover/large/bx182066-kqOV7WW1DAH4.jpg",
      "description": "Cecil Perdium, the Mercenary King, was killed in battle before he could avenge his family. As he faces death, he learns that Duke Delphine, the man who caused the downfall of his family, didn't work alone. Suddenly waking up as his teenage self, Cecil must work to both overcome his poor reputation and build up his strength to save his family. With their soldiers and knights defecting due to the harsh conditions they must endure, he has his work cut out for him. Can Cecil become the mighty warrior he once was and avert his family's fate?\n<br><br>\n(Source: WEBTOON)",
      "genres": [
        "Action",
        "Fantasy"
      ],
      "metadata": {
        "average_score": 80,
        "country_of_origin": "KR",
        "format": "MANGA"
      },
      "previous_score": 20318.0,
      "velocity": 0.002017915149128851
    },
    {
      "id": "anilist-anime-269",
      "title": "Bleach",
      "source": "AniList",
      "category": "anime",
      "score": 489582.0,
      "url": "https://anilist.co/anime/269",
      "image": "https://s4.anilist.co/file/anilistcdn/media/anime/cover/large/bx269-d2GmRkJbMopq.png",
      "description": "Ichigo Kurosaki is a rather normal high school student apart from the fact he has the ability to see ghosts. This ability never impacted his life in a major way until the day he encounters the Shinigami Kuchiki Rukia, who saves him and his family's lives from a Hollow, a corrupt spirit that devours human souls. \n<br><br>\nWounded during the fight against the Hollow, Rukia chooses the only option available to defeat the monster and passes her Shinigami powers to Ichigo. Now forced to act as a substitute until Rukia recovers, Ichigo hunts down the Hollows that plague his town. \n\n\n",
      "genres": [
        "Action",
        "Adventure",
        "Supernatural"
      ],
      "metadata": {
        "average_score": 79
      },
      "previous_score": 489196.0,
      "velocity": 0.0007890497878151088
    },
    {
      "id": "anilist-anime-21",
      "title": "ONE PIECE",
      "source": "AniList",
      "category": "anime",
      "score": 715898.0,
      "url": "https://anilist.co/anime/21",
      "image": "https://s4.anilist.co/file/anilistcdn/media/anime/cover/large/bx21-ELSYx3yMPcKM.jpg",
      "description": "Gold Roger was known as the Pirate King, the strongest and most infamous being to have sailed the Grand Line. The capture and death of Roger by the World Government brought a change throughout the world. His last words before his death revealed the location of the greatest treasure in the world, One Piece. It was this revelation that brought about the Grand Age of Pirates, men who dreamed of finding One Piece (which promises an unlimited amount of riches and fame), and quite possibly the most coveted of titles for the person who found it, the title of the Pirate King.<br><br>\nEnter Monkey D. Luffy, a 17-year-old boy that defies your standard definition of a pirate. Rather than the popular persona of a wicked, hardened, toothless pirate who ransacks villages for fun, Luffy’s reason for being a pirate is one of pure wonder; the thought of an exciting adventure and meeting new and intriguing people, along with finding One Piece, are his reasons of becoming a pirate. Following in the footsteps of his childhood hero, Luffy and his crew travel across the Grand Line, experiencing crazy adventures, unveiling dark mysteries and battling strong enemies, all in order to reach One Piece.<br><br>\n<b>*This includes the following special episodes:</b><br>\n- Chopperman to the Rescue! Protect the TV Station by the Shore! (Episode 336)<br>\n- The Strongest Tag-Team! Luffy and Toriko's Hard Struggle! (Episode 492)<br>\n- Team Formation! Save Chopper (Episode 542)<br>\n- History's Strongest Collaboration vs. Glutton of the Sea (Episode 590)<br>\n- 20th Anniversary! Special Romance Dawn (Episode 907)",
      "genres": [
        "Action",
        "Adventure",
        "Comedy",
        "Drama",
        "Fantasy"
      ],
      "metadata": {
        "average_score": 87
      },
      "previous_score": 715422.0,
      "velocity": 0.0006653415746230896
    },
    {
      "id": "anilist-manga-132029",
      "title": "Dandadan",
      "source": "AniList",
      "category": "manga",
      "score": 112154.0,
      "url": "https://anilist.co/manga/132029",
      "image": "https://s4.anilist.co/file/anilistcdn/media/manga/cover/large/bx132029-prGF4gePdSKv.jpg",
      "description": "Momo Ayase strikes up an unusual friendship with her school’s UFO fanatic, whom she nicknames “Okarun” because he has a name that is not to be said aloud. While Momo believes in spirits, she thinks aliens are nothing but nonsense. Her new friend, meanwhile, thinks the exact opposite. To settle matters, the two set out to prove each other wrong—Momo to a UFO hotspot and Okarun to a haunted tunnel! What unfolds next is a beautiful story of young love…and oddly horny aliens and spirits?\n<br><br>\n(Source: VIZ Media) \n<br><br>\n<i>Note: Nominated for the 15th Manga Taisho Award in 2022.</i>",
      "genres": [
        "Action",
        "Comedy",
        "Drama",
        "Romance",
        "Sci-Fi",
        "Supernatural"
      ],
      "metadata": {
        "average_score": 82,
        "country_of_origin": "JP",
        "format": "MANGA"
      },
      "previous_score": 112082.0,
      "velocity": 0.000642386823932478
    },
    {
      "id": "anilist-manga-30013",
      "title": "One Piece",
      "source": "AniList",
      "category": "manga",
      "score": 226082.0,
      "url": "https://anilist.co/manga/30013",
      "image": "https://s4.anilist.co/file/anilistcdn/media/manga/cover/large/bx30013-BeslEMqiPhlk.jpg",
      "description": "As a child, Monkey D. Luffy was inspired to become a pirate by listening to the tales of the buccaneer \"Red-Haired\" Shanks. But his life changed when Luffy accidentally ate the Gum-Gum Devil Fruit and gained the power to stretch like rubber...at the cost of never being able to swim again! Years later, still vowing to become the king of the pirates, Luffy sets out on his adventure...one guy alone in a rowboat, in search of the legendary \"One Piece,\" said to be the greatest treasure in the world...\n<br><br>\n(Source: VIZ Media)",
      "genres": [
        "Action",
        "Adventure",
        "Comedy",
        "Fantasy"
      ],
      "metadata": {
        "average_score": 91,
        "country_of_origin": "JP",
        "format": "MANGA"
      },
      "previous_score": 226011.0,
      "velocity": 0.0003141440018406184
    },
    {
      "id": "webnovel-book-the-scumbag%E2%80%99s-guide-to-heroism_35677809208460505",
      "title": "The Scumbag’s Guide To Heroism",
      "source": "WebNovel",
      "category": "web_novel",
      "score": 16.0,
      "url": "https://www.webnovel.com/book/the-scumbag%E2%80%99s-guide-to-heroism_35677809208460505",
      "image": "https://book-pic.webnovel.com/bookcover/35677809208460505?imageMogr2/thumbnail/600x&imageId=1780246597505",
      "description": "# ACTION # ROMANCE # SYSTEM # R18 # WEAKTOSTRONG # SUPERPOWERS # SLICEOFLIFE # SMUT # ACADEMY # ECCHI",
      "genres": [
        "Web Novel"
      ],
      "metadata": {
        "ranking_page": "https://www.webnovel.com/ranking/novel/season/best_sellers"
      },
      "previous_score": 16.0,
      "velocity": 0.0
    },
    {
      "id": "dreame-1646404864",
      "title": "True Luna",
      "source": "Dreame",
      "category": "romance",
      "score": 16.0,
      "url": "https://www.dreame.com/story/1646404864",
      "image": "https://files.dreame.com/images/2023/03/12/1635059837492846592640e5fc146a99.png@208w_300h_2e_53287592837a",
      "description": "I wanted to run to him, but I stopped myself when I saw how cold his stare was. What was going on?",
      "genres": [
        "Fantasy"
      ],
      "metadata": {
        "bid": 1646404864
      },
      "previous_score": 16.0,
      "velocity": 0.0
    },
    {
      "id": "webnovel-book-greymoor-academy-i-accidentally-bonded-with-four-lycan-royals!_35396013508215305",
      "title": "Greymoor Academy: I Accidentally Bonded With Four Lycan Royals!",
      "source": "WebNovel",
      "category": "web_novel",
      "score": 15.0,
      "url": "https://www.webnovel.com/book/greymoor-academy-i-accidentally-bonded-with-four-lycan-royals!_35396013508215305",
      "image": "https://book-pic.webnovel.com/bookcover/35396013508215305?imageMogr2/thumbnail/600x&imageId=1774058219314",
      "description": "# REVENGE # CAMPUS # WEREWOLF # LOVETRIANGLE # ENEMIESTOLOVERS # FATEDLOVE # ABUSEDFL # FORBIDDENLOVE # REJECTED # REVERSE HAREM",
      "genres": [
        "Web Novel"
      ],
      "metadata": {
        "ranking_page": "https://www.webnovel.com/ranking/novel/season/best_sellers"
      },
      "previous_score": 15.0,
      "velocity": 0.0
    },
    {
      "id": "dreame-1231429376",
      "title": "Her Triplet Alphas",
      "source": "Dreame",
      "category": "romance",
      "score": 15.0,
      "url": "https://www.dreame.com/story/1231429376",
      "image": "https://files.dreame.com/images/2020/11/09/13256427573642977285fa8b8a5add51.png@208w_300h_2e_53287592837a",
      "description": "I had never even had one boyfriend, now I had 3 mates?!",
      "genres": [
        "Paranormal"
      ],
      "metadata": {
        "bid": 1231429376
      },
      "previous_score": 15.0,
      "velocity": 0.0
    },
    {
      "id": "webnovel-book-betrayed-by-my-ex-marked-by-his-alpha-emperor-brother_35393754900224005",
      "title": "Betrayed by My Ex, Marked by His Alpha Emperor Brother",
      "source": "WebNovel",
      "category": "web_novel",
      "score": 14.0,
      "url": "https://www.webnovel.com/book/betrayed-by-my-ex-marked-by-his-alpha-emperor-brother_35393754900224005",
      "image": "https://book-pic.webnovel.com/bookcover/35393754900224005?imageMogr2/thumbnail/600x&imageId=1773995997681",
      "description": "# ROMANCE # R18 # WEAKTOSTRONG # WEREWOLF # HISTORICAL # ALPHA # ONENIGHTSTAND # FATEDMATE # BETRAYED",
      "genres": [
        "Web Novel"
      ],
      "metadata": {
        "ranking_page": "https://www.webnovel.com/ranking/novel/season/best_sellers"
      },
      "previous_score": 14.0,
      "velocity": 0.0
    },
    {
      "id": "dreame-742663424",
      "title": "The Rejected Luna's Prince",
      "source": "Dreame",
      "category": "romance",
      "score": 14.0,
      "url": "https://www.dreame.com/story/742663424",
      "image": "https://assets.dreame.com/cover/2024/07/01/180772480422979174466828689f1651.png",
      "description": "That day he made me his in every way possible...But I ended up with pregnant and rejected.",
      "genres": [
        "Romance"
      ],
      "metadata": {
        "bid": 742663424
      },
      "previous_score": 14.0,
      "velocity": 0.0
    },
    {
      "id": "dreame-2880119808",
      "title": "The Defiant Mate",
      "source": "Dreame",
      "category": "romance",
      "score": 13.0,
      "url": "https://www.dreame.com/story/2880119808",
      "image": "https://assets.dreame.com/cover/2024/08/08/182147560613974835266b48cf860d3d.png",
      "description": "I'm pregnant?! No, moon goddess, no! PREGNANCY TEST:POSITIVE  RESULT: 3 WEEKS PREGNANT",
      "genres": [
        "Fantasy"
      ],
      "metadata": {
        "bid": 2880119808
      },
      "previous_score": 13.0,
      "velocity": 0.0
    },
    {
      "id": "dreame-1570579456",
      "title": "The Rejected Wolf",
      "source": "Dreame",
      "category": "romance",
      "score": 12.0,
      "url": "https://www.dreame.com/story/1570579456",
      "image": "https://files.dreame.com/images/2022/07/05/154421336222391910462c3e062ed4c0.png@208w_300h_2e_53287592837a",
      "description": "Her mate rejected her when she fell pregnant with his child.",
      "genres": [
        "Paranormal"
      ],
      "metadata": {
        "bid": 1570579456
      },
      "previous_score": 12.0,
      "velocity": 0.0
    },
    {
      "id": "dreame-20390912",
      "title": "The Unwanted Bride Of Atticus Fawn",
      "source": "Dreame",
      "category": "romance",
      "score": 11.0,
      "url": "https://www.dreame.com/story/20390912",
      "image": "https://files.dreame.com/images/2022/07/22/155038237210369638462da51b8f3dcf.png@208w_300h_2e_53287592837a",
      "description": "And he didn't know how much I loved him. I've hidden it well.",
      "genres": [
        "Romance"
      ],
      "metadata": {
        "bid": 20390912
      },
      "previous_score": 11.0,
      "velocity": 0.0
    },
    {
      "id": "dreame-1411916544",
      "title": "Her Inner Power",
      "source": "Dreame",
      "category": "romance",
      "score": 10.0,
      "url": "https://www.dreame.com/story/1411916544",
      "image": "https://files.dreame.com/images/2022/06/22/153945276692854784062b28ebbe8bae.png@208w_300h_2e_53287592837a",
      "description": "Her soulmate is also her biggest enemy. What will she do?",
      "genres": [
        "Paranormal"
      ],
      "metadata": {
        "bid": 1411916544
      },
      "previous_score": 10.0,
      "velocity": 0.0
    },
    {
      "id": "goodnovel-book-The-Heartless-Alpha-s-Beloved-Luna_31001165452",
      "title": "The Heartless Alpha’s Beloved Luna",
      "source": "GoodNovel",
      "category": "romance",
      "score": 10.0,
      "url": "https://www.goodnovel.com/book/The-Heartless-Alpha-s-Beloved-Luna_31001165452",
      "image": "https://acf.goodnovel.com/book/202601/a89c920a786d425d24ace4a803166207a0985f570cc32829eb7b2c3ecda81927.jpg?v=1&p=1&w=1080&a=webp",
      "description": "Avery watched her boyfriend Ryan cheating with her half sister Zara right in front of her eyes on the Mating Day, the day she was meant to be claimed by Ryan as his chosen mate. The worse thing is that Ryan and Zara had the right to do so, because they just found out they were fated mates. Heartbroken, Avery fleed into the forest, only to fell into the arms of a dangerous stranger whose scent triggered her mating heat. Avery believed he was a rogue, so she just wanted one night of forbidden passion in the dark and ran away the next morning without even knowing what he looked like exactly. However, after she got home, she panicked as she found out she was marked by that stranger... Avery's father threatened to kill her if she couldn't secure a husband who could accept her. Just when Avery thought no one would want a marked girl, Alpha Gideon choose her as his bride, and something about him just seemed familiar....",
      "genres": [
        "Romance"
      ],
      "metadata": {
        "ranking_page": "https://www.goodnovel.com/"
      },
      "previous_score": 10.0,
      "velocity": 0.0
    },
    {
      "id": "dreame-1737958400",
      "title": "Surprising the Bully (True Love Series Book 1)",
      "source": "Dreame",
      "category": "romance",
      "score": 9.0,
      "url": "https://www.dreame.com/story/1737958400",
      "image": "https://assets.dreame.com/cover/2025/09/04/196363845830397952068b9bc71a1797.png",
      "description": "This gorgeous lady is that bullied girl? How can‘t I realize before!",
      "genres": [
        "YA&Teenfiction"
      ],
      "metadata": {
        "bid": 1737958400
      },
      "previous_score": 9.0,
      "velocity": 0.0
    },
    {
      "id": "goodnovel-book-Your-Uncle-s-My-Husband-Now-Back-Off-Ex_31001200284",
      "title": "Your Uncle’s My Husband Now—Back Off, Ex!",
      "source": "GoodNovel",
      "category": "romance",
      "score": 9.0,
      "url": "https://www.goodnovel.com/book/Your-Uncle-s-My-Husband-Now-Back-Off-Ex_31001200284",
      "image": "https://acf.goodnovel.com/book/202512/dd9d70146d0aaa2148e999644f7156f157f3e358313156cefe661f8c6e6ada9d.jpg?v=1&p=1&w=1080&a=webp",
      "description": "On their third wedding anniversary, Clark Summer gifted his wife a diamond necklace named \"Love Nyla,\" broadcasting his devotion to the world. But while the public swooned, Nyla sat alone in their empty home, staring at a photo sent by a stranger: her husband’s new secretary, Jordyn, wearing that same necklace, tangled in Clark’s arms.\nFor three years, Nyla had been the perfect, submissive wife. In return, she received betrayal, humiliation from her mother-in-law, and Clark’s sickening justification that his affair was merely a \"physical necessity\" while he still loved her. He believed Nyla was trapped, tethered to him by her father’s astronomical medical bills. He thought she would swallow the insults and raise his mistress's child.\nHe was wrong.\nSelling their mansion, gathering evidence, and delivering irrefutable proof of her infidelity… Nera turned and left, donning a white lab coat instead of an apron, transforming overnight into a top-tier pharmaceutical researcher who had astonished the industry. \nWhen Clark, with belated repentance and red-eyed pleading for her return, saw his icy ex-wife being gently embraced by his uncle Damon, he saw the aloof man before him. The superior man coldly glanced at his nephew, his voice low and dangerous: \"What are you calling 'wife'? Call her 'auntie'.\"",
      "genres": [
        "Romance"
      ],
      "metadata": {
        "ranking_page": "https://www.goodnovel.com/"
      },
      "previous_score": 9.0,
      "velocity": 0.0
    },
    {
      "id": "dreame-3391824640",
      "title": "My Mate is an Omega",
      "source": "Dreame",
      "category": "romance",
      "score": 8.0,
      "url": "https://www.dreame.com/story/3391824640",
      "image": "https://files.dreame.com/images/2022/08/30/1564736567288070144630e8a1b46c5d.png@208w_300h_2e_53287592837a",
      "description": "Can an Omega couple prove how powerful they can become, or will the twists and turns of life tear them apart?",
      "genres": [
        "Romance"
      ],
      "metadata": {
        "bid": 3391824640
      },
      "previous_score": 8.0,
      "velocity": 0.0
    },
    {
      "id": "goodnovel-book-Second-Chance-for-the-Barren-Luna_31001064899",
      "title": "Second Chance for the Barren Luna",
      "source": "GoodNovel",
      "category": "romance",
      "score": 8.0,
      "url": "https://www.goodnovel.com/book/Second-Chance-for-the-Barren-Luna_31001064899",
      "image": "https://acf.goodnovel.com/book/202658/28f6ca955614a0ab96b4d9765d3611118f31a5bb63ad1afd440e89588aa74276.jpg?v=1&p=1&w=1080&a=webp",
      "description": "“If you can’t provide an heir, you’re a Luna in name only. I need more than a worthless, barren omega cosplaying as a Luna!”\n\nMy Alpha husband Jason’s words cut deeper than any silver blade. For three years, I have kept the truth from him. He thinks he married a weak omega. But the truth? I am the Alpha King’s daughter.\n\nI wait eagerly for his return from a victorious war, ready to reveal who I truly am. Only to find him walking back with his mistress, Viki, who has already carrying his pup.\n\n“You have two options,” Jason snarls, eyes cold. “Lose your status as Luna and go back to being a useless omega. Or stay for Viki and help raise my heir.”\n\nPushed to my breaking point, I accept his rejection and return to my father’s kingdom. I think my heart is dead but fate has led me to a dangerous second-chance mate. Worse, Jason can’t let me go that easily.",
      "genres": [
        "Romance"
      ],
      "metadata": {
        "ranking_page": "https://www.goodnovel.com/"
      },
      "previous_score": 8.0,
      "velocity": 0.0
    },
    {
      "id": "dreame-696460032",
      "title": "Seven Days Before Divorce",
      "source": "Dreame",
      "category": "romance",
      "score": 7.0,
      "url": "https://www.dreame.com/story/696460032",
      "image": "https://files.dreame.com/images/2022/06/13/153630161370117324862a717fec55a9.png@208w_300h_2e_53287592837a",
      "description": "\"Ah... Too deep, honey. Cirrus, slow down, you are hurting me.\"“Cirrus? But my name isn’t Cirrus...”",
      "genres": [
        "Romance"
      ],
      "metadata": {
        "bid": 696460032
      },
      "previous_score": 7.0,
      "velocity": 0.0
    },
    {
      "id": "goodnovel-book-His-Plump-Mate_31001222962",
      "title": "His Plump Mate",
      "source": "GoodNovel",
      "category": "romance",
      "score": 7.0,
      "url": "https://www.goodnovel.com/book/His-Plump-Mate_31001222962",
      "image": "https://acf.goodnovel.com/book/202511/1f46a28711a8c933c5db6bdeb2f147a343bbb579207d302aa5a1e5d714ed7fed.jpg?v=1&p=1&w=1080&a=webp",
      "description": "His Plump Mate is a Werewolf novel written by BUCHANAN that covers Werewolf, Steamy, Alpha. Read full chapters of this story online on GoodNovel.",
      "genres": [
        "Romance"
      ],
      "metadata": {
        "ranking_page": "https://www.goodnovel.com/"
      },
      "previous_score": 7.0,
      "velocity": 0.0
    },
    {
      "id": "dreame-1094329344",
      "title": "Big, Bold, And Beautiful.",
      "source": "Dreame",
      "category": "romance",
      "score": 6.0,
      "url": "https://www.dreame.com/story/1094329344",
      "image": "https://files.dreame.com/images/2022/08/04/155507799528128921662eb66dc471a3.png@208w_300h_2e_53287592837a",
      "description": "When pluz-size girl meets her billionaire Alpha",
      "genres": [
        "Romance"
      ],
      "metadata": {
        "bid": 1094329344
      },
      "previous_score": 6.0,
      "velocity": 0.0
    },
    {
      "id": "goodnovel-book-Billionaire-s-Match_31001148338",
      "title": "Billionaire's Match",
      "source": "GoodNovel",
      "category": "romance",
      "score": 6.0,
      "url": "https://www.goodnovel.com/book/Billionaire-s-Match_31001148338",
      "image": "https://acf.goodnovel.com/book/202512/483b3bc53d3d95d1d1dc8e8dc6346c35c2b245d28a13e1e7ee37fc4f31838ff2.jpg?v=1&p=1&w=1080&a=webp",
      "description": "Billionaire's Match is a Romance novel written by Tangy Candy that covers Drama, Fast-Paced Plot, Sweet Love. Read full chapters of this story online on GoodNovel.",
      "genres": [
        "Romance"
      ],
      "metadata": {
        "ranking_page": "https://www.goodnovel.com/"
      },
      "previous_score": 6.0,
      "velocity": 0.0
    },
    {
      "id": "dreame-2235114496",
      "title": "His Silent Temptation",
      "source": "Dreame",
      "category": "romance",
      "score": 5.0,
      "url": "https://www.dreame.com/story/2235114496",
      "image": "https://files.dreame.com/images/2022/07/22/155029417127186841662d9ff94a9af0.png@208w_300h_2e_53287592837a",
      "description": "I’m jealous of your heart pumping inside of you and I’m not",
      "genres": [
        "Romance"
      ],
      "metadata": {
        "bid": 2235114496
      },
      "previous_score": 5.0,
      "velocity": 0.0
    },
    {
      "id": "goodnovel-book-Married-at-First-Sight_31000384431",
      "title": "Married at First Sight",
      "source": "GoodNovel",
      "category": "romance",
      "score": 5.0,
      "url": "https://www.goodnovel.com/book/Married-at-First-Sight_31000384431",
      "image": "https://acf.goodnovel.com/book/202208/Married-at-First-Sight/f0b5eb8152a5c2a3b57c993c0e60c9d94549f934a29d96cbecce2c282d8f4269.jpg?v=1&p=1&w=1080&a=webp",
      "description": "The novel Married at First Sight is a Billionaire, telling a story of Since the day Serenity got hitched to a stranger on their blind date, she had assumed married life would be ordinary but respectful and mundane. It never crossed her mind that her new husband would be clingy like a piece of gum stuck to the bottom of a shoe. To her utmost surprise, he could make... Married at First Sight PDF",
      "genres": [
        "Romance"
      ],
      "metadata": {
        "ranking_page": "https://www.goodnovel.com/"
      },
      "previous_score": 5.0,
      "velocity": 0.0
    },
    {
      "id": "dreame-1317150208",
      "title": "Enslaved By The Alpha",
      "source": "Dreame",
      "category": "romance",
      "score": 4.0,
      "url": "https://www.dreame.com/story/1317150208",
      "image": "https://assets.dreame.com/cover/2023/09/15/170260495091342950465041a0bb531f.png",
      "description": "The woman he had planned to kidnap and kill was his very own mate !",
      "genres": [
        "Paranormal"
      ],
      "metadata": {
        "bid": 1317150208
      },
      "previous_score": 4.0,
      "velocity": 0.0
    },
    {
      "id": "goodnovel-book-CLAIMED-BY-THE-MAFIA-DON_31001293897",
      "title": "CLAIMED BY THE MAFIA DON",
      "source": "GoodNovel",
      "category": "romance",
      "score": 4.0,
      "url": "https://www.goodnovel.com/book/CLAIMED-BY-THE-MAFIA-DON_31001293897",
      "image": "https://acf.goodnovel.com/book/202601/8bf3dc2930c8594b95cb8956fdadcecfe5c1e90e58d4415a32c3435acdd20da5.jpg?v=1&p=1&w=1080&a=webp",
      "description": "CLAIMED BY THE MAFIA DON is a Mafia novel written by JacqueAuthor  that covers Dark Romance, Contemporary, Ruthless. Read full chapters of this story online on GoodNovel.",
      "genres": [
        "Romance"
      ],
      "metadata": {
        "ranking_page": "https://www.goodnovel.com/"
      },
      "previous_score": 4.0,
      "velocity": 0.0
    },
    {
      "id": "dreame-850797312",
      "title": "Sky's Rejection",
      "source": "Dreame",
      "category": "romance",
      "score": 3.0,
      "url": "https://www.dreame.com/story/850797312",
      "image": "https://files.dreame.com/images/2022/01/03/147784537540583014461d26e5a4bdf2.png@208w_300h_2e_53287592837a",
      "description": "Until she met her second chance, the Royal Alpha King",
      "genres": [
        "Paranormal"
      ],
      "metadata": {
        "bid": 850797312
      },
      "previous_score": 3.0,
      "velocity": 0.0
    },
    {
      "id": "goodnovel-book-The-Alpha-s-Unwanted-Luna_31001153954",
      "title": "The Alpha's Unwanted Luna Series",
      "source": "GoodNovel",
      "category": "romance",
      "score": 3.0,
      "url": "https://www.goodnovel.com/book/The-Alpha-s-Unwanted-Luna_31001153954",
      "image": "https://acf.goodnovel.com/book/202640/5cc80cbafb79aa1dd9e17ed34a4586496ee10b9ca1002e466f574941d419d6d6.jpg?v=1&p=1&w=1080&a=webp",
      "description": "The Alpha's Unwanted Luna Series is a Werewolf novel written by Miss L that covers Werewolf, Alpha, Warrior. Read full chapters of this story online on GoodNovel.",
      "genres": [
        "Romance"
      ],
      "metadata": {
        "ranking_page": "https://www.goodnovel.com/"
      },
      "previous_score": 3.0,
      "velocity": 0.0
    },
    {
      "id": "dreame-598367488",
      "title": "Holiday Hockey Tale: The Icebreaker's Impasse",
      "source": "Dreame",
      "category": "romance",
      "score": 2.0,
      "url": "https://www.dreame.com/story/598367488",
      "image": "https://assets.dreame.com/cover/2025/03/21/190312864397959577667dd9a49fe200.png@350w_500h.webp",
      "description": "Luci Forrester is a college senior. She hasn't had the best college experience and is counting down the days to leave the hell that is Kenton University. If she didn't depend on her scholarship, she'd...",
      "genres": [
        "Romance"
      ],
      "metadata": {
        "bid": 598367488
      },
      "previous_score": 2.0,
      "velocity": 0.0
    },
    {
      "id": "webnovel-book-global-deities-rising-as-wood-elves'-god_35234032408256805",
      "title": "Global Deities: Rising as Wood Elves' God",
      "source": "WebNovel",
      "category": "web_novel",
      "score": 11.0,
      "url": "https://www.webnovel.com/book/global-deities-rising-as-wood-elves'-god_35234032408256805",
      "image": "https://book-pic.webnovel.com/bookcover/35234032408256805?imageMogr2/thumbnail/600x&imageId=1777342792009",
      "description": "# SYSTEM # WEAKTOSTRONG # KINGDOMBUILDING",
      "genres": [
        "Web Novel"
      ],
      "metadata": {
        "ranking_page": "https://www.webnovel.com/ranking/novel/season/best_sellers"
      },
      "previous_score": 13.0,
      "velocity": -0.15384615384615385
    },
    {
      "id": "webnovel-book-infinite-evolution-dominating-the-apocalypse-with-my-god-tier-items_35460563000367305",
      "title": "Infinite Evolution: Dominating The Apocalypse With My God Tier Items",
      "source": "WebNovel",
      "category": "web_novel",
      "score": 9.0,
      "url": "https://www.webnovel.com/book/infinite-evolution-dominating-the-apocalypse-with-my-god-tier-items_35460563000367305",
      "image": "https://book-pic.webnovel.com/bookcover/35460563000367305?imageMogr2/thumbnail/600x&imageId=1778661436014",
      "description": "# ACTION # ROMANCE # ADVENTURE # SYSTEM # DARK # SUPERPOWERS # OVERPOWERED # SURVIVAL # APOCALYPSE # GENES",
      "genres": [
        "Web Novel"
      ],
      "metadata": {
        "ranking_page": "https://www.webnovel.com/ranking/novel/season/best_sellers"
      },
      "previous_score": 11.0,
      "velocity": -0.18181818181818182
    },
    {
      "id": "webnovel-book-rebate-king-every-beauty-i-spoil-makes-me-a-billionaire_35492500200946605",
      "title": "Rebate King: Every Beauty I Spoil Makes Me a Billionaire",
      "source": "WebNovel",
      "category": "web_novel",
      "score": 7.0,
      "url": "https://www.webnovel.com/book/rebate-king-every-beauty-i-spoil-makes-me-a-billionaire_35492500200946605",
      "image": "https://book-pic.webnovel.com/bookcover/35492500200946605?imageMogr2/thumbnail/600x&imageId=1779867926769",
      "description": "# ROMANCE # SYSTEM # R18 # HAREM # SLICEOFLIFE # GENIUS # SMUT # CAMPUS # URBAN # FACESLAPPING",
      "genres": [
        "Web Novel"
      ],
      "metadata": {
        "ranking_page": "https://www.webnovel.com/ranking/novel/season/best_sellers"
      },
      "previous_score": 10.0,
      "velocity": -0.3
    },
    {
      "id": "webnovel-book-reborn-with-a-space-hoarding-food-and-raising-my-kid_35479981200689605",
      "title": "Reborn with a Space: Hoarding Food and Raising My Kid",
      "source": "WebNovel",
      "category": "web_novel",
      "score": 8.0,
      "url": "https://www.webnovel.com/book/reborn-with-a-space-hoarding-food-and-raising-my-kid_35479981200689605",
      "image": "https://book-pic.webnovel.com/bookcover/35479981200689605?imageMogr2/thumbnail/600x&imageId=1778213367628",
      "description": "# WEAKTOSTRONG # APOCALYPSE # REBIRTH # HEALING # FARMING # STORAGESPACE",
      "genres": [
        "Web Novel"
      ],
      "metadata": {
        "ranking_page": "https://www.webnovel.com/ranking/novel/season/best_sellers"
      },
      "previous_score": 12.0,
      "velocity": -0.3333333333333333
    },
    {
      "id": "webnovel-book-her-food-livestream-broke-the-galaxy_34992979700618405",
      "title": "Her Food Livestream Broke the Galaxy",
      "source": "WebNovel",
      "category": "web_novel",
      "score": 5.0,
      "url": "https://www.webnovel.com/book/her-food-livestream-broke-the-galaxy_34992979700618405",
      "image": "https://book-pic.webnovel.com/bookcover/34992979700618405?imageMogr2/thumbnail/600x&imageId=1775183955367",
      "description": "# WEAKTOSTRONG # STRONGFL # SUPERSTAR # SPACE # FEELINGGOOD # GOURMET",
      "genres": [
        "Web Novel"
      ],
      "metadata": {
        "ranking_page": "https://www.webnovel.com/ranking/novel/season/best_sellers"
      },
      "previous_score": 9.0,
      "velocity": -0.4444444444444444
    },
    {
      "id": "webnovel-book-my-apocalypse-system-arrives-10-years-early_35233954100293305",
      "title": "My Apocalypse System Arrives 10 Years Early",
      "source": "WebNovel",
      "category": "web_novel",
      "score": 3.0,
      "url": "https://www.webnovel.com/book/my-apocalypse-system-arrives-10-years-early_35233954100293305",
      "image": "https://book-pic.webnovel.com/bookcover/35233954100293305?imageMogr2/thumbnail/600x&imageId=1776306636823",
      "description": "# SYSTEM # KINGDOMBUILDING",
      "genres": [
        "Web Novel"
      ],
      "metadata": {
        "ranking_page": "https://www.webnovel.com/ranking/novel/season/best_sellers"
      },
      "previous_score": 6.0,
      "velocity": -0.5
    },
    {
      "id": "anilist-manga-106130",
      "title": "Blue Lock",
      "source": "AniList",
      "category": "manga",
      "score": 119101.0,
      "url": "https://anilist.co/manga/106130",
      "image": "https://s4.anilist.co/file/anilistcdn/media/manga/cover/large/bx106130-yPNeuSu75ey1.jpg",
      "description": "After a disastrous defeat at the 2018 World Cup, Japan's team struggles to regroup. But what's missing? An absolute Ace Striker, who can guide them to the win. The Japan Football Union is hell-bent on creating a striker who hungers for goals and thirsts for victory, and who can be the decisive instrument in turning around a losing match...and to do so, they've gathered 300 of Japan's best and brightest youth players. Who will emerge to lead the team...and will they be able to out-muscle and out-ego everyone who stands in their way?\n<br><br>\n(Source: Kodansha USA)\n<br><br>\n<i>Note: Winner of the 45th Kodansha Manga Award in the Shounen Category in 2021.</i>",
      "genres": [
        "Action",
        "Drama",
        "Sports"
      ],
      "metadata": {
        "average_score": 82,
        "country_of_origin": "JP",
        "format": "MANGA"
      },
      "previous_score": null,
      "velocity": null
    },
    {
      "id": "anilist-anime-169580",
      "title": "I Made Friends with the Second Prettiest Girl in My Class",
      "source": "AniList",
      "category": "anime",
      "score": 72712.0,
      "url": "https://anilist.co/anime/169580",
      "image": "https://s4.anilist.co/file/anilistcdn/media/anime/cover/large/bx169580-nXxpmqu6UVux.jpg",
      "description": "Maki Maehara, the class outcast, finally makes his first friend: Umi Asanagi, the second-prettiest girl in class and the center of everyone’s attention. He’s convinced she’s out of his league, but as their unlikely friendship grows, Maki starts to wonder…could there be more than just friendship between them?<br>\n<br>\n(Source: Crunchyroll)",
      "genres": [
        "Comedy",
        "Romance"
      ],
      "metadata": {
        "average_score": 80
      },
      "previous_score": null,
      "velocity": null
    },
    {
      "id": "anilist-anime-199547",
      "title": "MARRIAGETOXIN",
      "source": "AniList",
      "category": "anime",
      "score": 67521.0,
      "url": "https://anilist.co/anime/199547",
      "image": "https://s4.anilist.co/file/anilistcdn/media/anime/cover/large/bx199547-LAaG3cmKCGhr.jpg",
      "description": "For centuries, the deadly arts have been perfected by those known as the Masters.\nAmong them, the Poison Masters of the Five Great Families hold the most fearsome power and influence. \nHikaru Gero, heir to the Poison Masters’ Gero Family, has lived his entire life in the underworld, far removed from love or marriage.\nBut when the Gero Family head decrees that Hikaru’s sister must bear an heir to preserve the bloodline—by force if necessary—Hikaru resolves to protect her at all costs.\nIt is then that Hikaru encounters Mei Kinosaki, a brilliant marriage swindler who becomes the target of his latest job.\nRealizing that the only way of solving the family succession problem and protecting his sister is through marriage, Hikaru impulsively asks Mei for help in finding a bride.\n<br><br>\n(Source: EMOTION Label Channel)",
      "genres": [
        "Action",
        "Comedy",
        "Drama",
        "Romance"
      ],
      "metadata": {
        "average_score": 75
      },
      "previous_score": null,
      "velocity": null
    },
    {
      "id": "anilist-manga-106929",
      "title": "Eleceed",
      "source": "AniList",
      "category": "manhwa",
      "score": 43642.0,
      "url": "https://anilist.co/manga/106929",
      "image": "https://s4.anilist.co/file/anilistcdn/media/manga/cover/large/bx106929-flAUvHZDUz5v.jpg",
      "description": "Jiwoo is a kind-hearted young man who harnesses the lightning quick reflexes of a cat to secretly make the world a better place – one saved little child or foster pet at a time. Kayden is a secret agent on the run, who finds himself stuck in the body of a…um…decidedly fat old fluffy cat. Together, armed with Jiwoo’s super powers and Kayden’s uber-smarts, they’re out to fight those forces who would let evil rule this world. That is, if they can stand each other long enough to get the job done.\n<br><br>(Source: WEBTOONS)",
      "genres": [
        "Action",
        "Comedy",
        "Supernatural"
      ],
      "metadata": {
        "average_score": 85,
        "country_of_origin": "KR",
        "format": "MANGA"
      },
      "previous_score": null,
      "velocity": null
    },
    {
      "id": "anilist-anime-194393",
      "title": "I Want to End this Love Game",
      "source": "AniList",
      "category": "anime",
      "score": 42470.0,
      "url": "https://anilist.co/anime/194393",
      "image": "https://s4.anilist.co/file/anilistcdn/media/anime/cover/large/bx194393-0H9yYABu6y0i.jpg",
      "description": "Childhood friends Yukiya and Miku share everything…except their feelings. Ever since sixth grade, they’ve played a “love game”: they take turns saying “I love you” and whoever gets flustered first loses. Now in high school, their hearts are closer than ever—but will they finally find the courage to confess?\n<br><br>\n(Source: Crunchyroll)",
      "genres": [
        "Comedy",
        "Romance"
      ],
      "metadata": {
        "average_score": 72
      },
      "previous_score": null,
      "velocity": null
    },
    {
      "id": "anilist-manga-132144",
      "title": "Return of the Blossoming Blade",
      "source": "AniList",
      "category": "manhwa",
      "score": 41004.0,
      "url": "https://anilist.co/manga/132144",
      "image": "https://s4.anilist.co/file/anilistcdn/media/manga/cover/large/bx132144-i5B4VnG9sRgh.png",
      "description": "When Cheong-Myeong of the Mount Hua Sect awakens a hundred years in the future, his last memories are of a bloody battle against the Leader of the Demonic Cult, the evil Cheon-Ma. The battle almost saw the end of the Ten Great Sects of ancient China, when Cheong-Myeong ended the hard-fought struggle by striking down Cheon-Ma. Soon after, he succumbed to his wounds, filled with regret at their pyrrhic victory. All is not lost, however, as he awakens to his second chance at life. Shocked to find his beloved Mount Hua Sect reduced to a mere shadow of itself in the present day, Cheong-Myeong embarks on a journey to restore Mount Hua to its former glory.<br>\n<br>\n(Source: WEBTOON, edited)",
      "genres": [
        "Action",
        "Adventure",
        "Fantasy"
      ],
      "metadata": {
        "average_score": 84,
        "country_of_origin": "KR",
        "format": "MANGA"
      },
      "previous_score": null,
      "velocity": null
    },
    {
      "id": "anilist-manga-159930",
      "title": "The Infinite Mage",
      "source": "AniList",
      "category": "manhwa",
      "score": 36949.0,
      "url": "https://anilist.co/manga/159930",
      "image": "https://s4.anilist.co/file/anilistcdn/media/manga/cover/large/bx159930-qK1P4BNQL0zG.jpg",
      "description": "After Sirone was abandoned in a stable, he was found by a family of hunters and raised in a loving home. Despite the hardships of the peasant life, he learned how to read from a young age and became obsessed with books, especially ones on the history of magic. One day, he has an unlikely encounter with a mage and learns how to enter the \"spirit zone,\" the first step to learning how to use magic. Although they say only nobles can be mages, will Sirone be able to prove his infinite potential?\n<br><br>\n(Source: Tapas)",
      "genres": [
        "Action",
        "Adventure",
        "Drama",
        "Fantasy"
      ],
      "metadata": {
        "average_score": 78,
        "country_of_origin": "KR",
        "format": "MANGA"
      },
      "previous_score": null,
      "velocity": null
    },
    {
      "id": "anilist-manga-170400",
      "title": "The Stellar Swordmaster",
      "source": "AniList",
      "category": "manhwa",
      "score": 27463.0,
      "url": "https://anilist.co/manga/170400",
      "image": "https://s4.anilist.co/file/anilistcdn/media/manga/cover/large/bx170400-yMIuOIboWuoO.jpg",
      "description": "The so-called “Lighthouse of the North,” the prosperous trading town of Schoarra, hides a dark underbelly: seedy slums ruled by five ruthless crime bosses. When streetwise orphan Vlad finds the brothel he works for decimated by a disgraced knight, he turns to the path of the blade, pledging himself to the pursuit of power by sword. Blessed with the ability to seek wisdom from his sentient sword, Vlad embarks upon a journey of growth and peril as swordsman in service to the powerful House Vayezid.<br>\n<br>\n(Source: WEBTOON)",
      "genres": [
        "Action",
        "Adventure",
        "Fantasy"
      ],
      "metadata": {
        "average_score": 82,
        "country_of_origin": "KR",
        "format": "MANGA"
      },
      "previous_score": null,
      "velocity": null
    },
    {
      "id": "anilist-manga-122063",
      "title": "Shangri-La Frontier",
      "source": "AniList",
      "category": "manga",
      "score": 20805.0,
      "url": "https://anilist.co/manga/122063",
      "image": "https://s4.anilist.co/file/anilistcdn/media/manga/cover/large/bx122063-j2wIvwb6yzPM.jpg",
      "description": "Second year high school student Rakuro Hizutome is interested in one thing only: finding \"shitty games\" and beating the crap out of them. His gaming skills are second to none, and no game is too bad for him to enjoy. So when he's introduced to the new VR game Shangri-La Frontier, he does what he does best—min-maxes and skips the prologue to jump straight into the action. But can even an expert gamer like Rakuro discover all the secrets that Shangri-La Frontier hides...?\n<br><br>\n(Source: Kodansha USA)\n<br/>",
      "genres": [
        "Action",
        "Adventure",
        "Comedy",
        "Fantasy",
        "Sci-Fi"
      ],
      "metadata": {
        "average_score": 81,
        "country_of_origin": "JP",
        "format": "MANGA"
      },
      "previous_score": null,
      "velocity": null
    },
    {
      "id": "anilist-manga-170894",
      "title": "The 100th Regression of the Max-Level Player",
      "source": "AniList",
      "category": "manhwa",
      "score": 20454.0,
      "url": "https://anilist.co/manga/170894",
      "image": "https://s4.anilist.co/file/anilistcdn/media/manga/cover/large/bx170894-oS4T4u9WqHoj.png",
      "description": "The world was embroiled in a death game involving individuals from ages 15 to 29. Thrown into a game devoid of empathy and compassion, Min Ryu had no choice but to fight for his survival. For the 99th time, he finally made it to the end of the game. Standing alone in front of the final boss’s chamber, Min Ryu was greeted with betrayal as the system killed him for not having four more players with him. On his 100th and final attempt, can Min Ryu find the help he needs to end this ruthless game?<br>\n<br>\n(Source: Tapas)",
      "genres": [
        "Action",
        "Adventure",
        "Fantasy",
        "Supernatural"
      ],
      "metadata": {
        "average_score": 77,
        "country_of_origin": "KR",
        "format": "MANGA"
      },
      "previous_score": null,
      "velocity": null
    },
    {
      "id": "anilist-manga-167834",
      "title": "The Martial God Who Regressed Back to Level 2",
      "source": "AniList",
      "category": "manhwa",
      "score": 18624.0,
      "url": "https://anilist.co/manga/167834",
      "image": "https://s4.anilist.co/file/anilistcdn/media/manga/cover/large/bx167834-QgyPJ7tOMGqA.png",
      "description": "Earth lost the fight for survival in the BattleNet system and humanity now faces eradication. However, Jihan Seong is given another chance. He has returned three years into the past before BattleNet became a life-or-death game. With his knowledge of the future, he’s determined to become the strongest player. Will Jihan be able to change the fate of humanity? And more importantly, can he protect the ones he loves from those who want him to fail?<br><br>(Source: Tapas)",
      "genres": [
        "Action",
        "Fantasy"
      ],
      "metadata": {
        "average_score": 74,
        "country_of_origin": "KR",
        "format": "MANGA"
      },
      "previous_score": null,
      "velocity": null
    },
    {
      "id": "anilist-anime-195268",
      "title": "The Most Heretical Last Boss Queen: From Villainess to Savior Season 2",
      "source": "AniList",
      "category": "anime",
      "score": 18548.0,
      "url": "https://anilist.co/anime/195268",
      "image": "https://s4.anilist.co/file/anilistcdn/media/anime/cover/large/bx195268-HkEv0z9iTCJK.jpg",
      "description": "The second season of <i>Higeki no Genkyou to Naru Saikyou Gedou Last Boss Joou wa Tami no Tame ni Tsukushimasu.</i>",
      "genres": [
        "Comedy",
        "Fantasy",
        "Romance"
      ],
      "metadata": {
        "average_score": 69
      },
      "previous_score": null,
      "velocity": null
    },
    {
      "id": "anilist-manga-169272",
      "title": "Tune In to the Midnight Heart",
      "source": "AniList",
      "category": "manga",
      "score": 16664.0,
      "url": "https://anilist.co/manga/169272",
      "image": "https://s4.anilist.co/file/anilistcdn/media/manga/cover/large/bx169272-1a2RZ43tqOdw.jpg",
      "description": "When Arisu Yamabuki was all alone in bed at night, he was able to find solace in the voice of a radio host who went by “Apollo.” However, one day, she simply stopped broadcasting without any explanation. Years then passed, and Arisu is now a second-year high-schooler. He makes it his mission to search for Apollo, as there is something he wants to tell her. He doesn’t know what she looks like, or even what her real name is, but he manages to get some leads on her in his school’s broadcasting club. That’s where he meets four girls who all dream to get a job where they can make full use of their voices! Just who is Apollo, and how will those four’s dreams pan out?\n<br><br>\n(Source: K MANGA)",
      "genres": [
        "Comedy",
        "Romance"
      ],
      "metadata": {
        "average_score": 83,
        "country_of_origin": "JP",
        "format": "MANGA"
      },
      "previous_score": null,
      "velocity": null
    },
    {
      "id": "anilist-manga-180422",
      "title": "Akira Failing in Love",
      "source": "AniList",
      "category": "manga",
      "score": 13550.0,
      "url": "https://anilist.co/manga/180422",
      "image": "https://s4.anilist.co/file/anilistcdn/media/manga/cover/large/bx180422-dRRQ8aeSAYum.jpg",
      "description": "Akira returns to the countryside for high school with a plan to win the heart of her childhood crush! They're both fools in love… because she's too dense to figure out he likes her back!<br><br>(Source: VIZ Media)",
      "genres": [
        "Comedy",
        "Romance"
      ],
      "metadata": {
        "average_score": 75,
        "country_of_origin": "JP",
        "format": "MANGA"
      },
      "previous_score": null,
      "velocity": null
    },
    {
      "id": "anilist-manga-169904",
      "title": "Tsumiki Ogami's Not-So-Ordinary Life",
      "source": "AniList",
      "category": "manga",
      "score": 13482.0,
      "url": "https://anilist.co/manga/169904",
      "image": "https://s4.anilist.co/file/anilistcdn/media/manga/cover/large/bx169904-6gvkXMNpq66N.jpg",
      "description": "Yutaka Shinso is constantly worried about what other people think of him. Hoping to turn over a new leaf, he changes high schools, but there’s something strange afoot: vampires, ogres, and all manner of supernatural beings walk the halls! Yutaka is particularly drawn to Tsumiki Ogami, a confident and popular werewolf. Will Tsumiki be the one to help Yutaka overcome his insecurities?\n<br><br>\n(Source: VIZ Media)\n<br><br>\n<i>Note:<br>\n- Placed third in the Tsugimanga 2024 Award in the Print Manga Category.</i>",
      "genres": [
        "Comedy",
        "Romance",
        "Supernatural"
      ],
      "metadata": {
        "average_score": 77,
        "country_of_origin": "JP",
        "format": "MANGA"
      },
      "previous_score": null,
      "velocity": null
    },
    {
      "id": "goodnovel-book-The-Alpha-Slipped-Inside-The-Wrong-Sister_31001351136",
      "title": "The Alpha Slipped Inside The Wrong Sister",
      "source": "GoodNovel",
      "category": "romance",
      "score": 16.0,
      "url": "https://www.goodnovel.com/book/The-Alpha-Slipped-Inside-The-Wrong-Sister_31001351136",
      "image": "https://acf.goodnovel.com/book/202604/9b7dc8042fbb49a32220b24faf50b6c8045408426824655a82fa674c53672efa.jpg?v=1&p=1&w=1080&a=webp",
      "description": "The bed was wet beneath me, soaked by the juices that flowed from between my thighs. A grunt, one so husky brushed against my ear as he moved in and out of me.\r\n\r\n\"Don't tell Kimberly,\" Alpha Ryan groaned as he pushes his cock deeper until the tip brushed a tender spot. I shudder beneath him. Kimberly was his future Luna. She was also my sister.\r\n\r\nI looked up at him beneath my lashes. \"Don't tell my sister you slipped inside the wrong one?\"",
      "genres": [
        "Romance"
      ],
      "metadata": {
        "ranking_page": "https://www.goodnovel.com/"
      },
      "previous_score": null,
      "velocity": null
    },
    {
      "id": "goodnovel-book-Seducing-My-Ex-s-Father-In-Law_31000825294",
      "title": "Seducing My Ex's Father In Law",
      "source": "GoodNovel",
      "category": "romance",
      "score": 14.0,
      "url": "https://www.goodnovel.com/book/Seducing-My-Ex-s-Father-In-Law_31000825294",
      "image": "https://acf.goodnovel.com/book/202409/d6033d607d3ece71d9e6744824c3ec4bc7d3adad788298c39183af28c6211c5f.jpg?v=1&p=1&w=1080&a=webp",
      "description": "Judy’s fated mate rejected her to marry the Lycan Chairman - Gavin’s daughter. As if that wasn’t bad enough, he ruined her family and tried to make her his secret mistress! \r\nJudy’s response? “I’d rather sleep with your father-in-law than ever be with you!”\r\nGavin is known for his power, wealth, and being the ultimate playboy who never sleeps with the same woman twice. \r\nBut Judy’s about to break all his rules… again and again.",
      "genres": [
        "Romance"
      ],
      "metadata": {
        "ranking_page": "https://www.goodnovel.com/"
      },
      "previous_score": null,
      "velocity": null
    },
    {
      "id": "webnovel-book-reborn-with-infinite-system-points-i-gathered-all-sss-classes!_35479981708644005",
      "title": "Reborn with Infinite System Points, I Gathered All SSS Classes!",
      "source": "WebNovel",
      "category": "web_novel",
      "score": 13.0,
      "url": "https://www.webnovel.com/book/reborn-with-infinite-system-points-i-gathered-all-sss-classes!_35479981708644005",
      "image": "https://book-pic.webnovel.com/bookcover/35479981708644005?imageMogr2/thumbnail/600x&imageId=1774877509893",
      "description": "# ACTION # ADVENTURE # SYSTEM # REINCARNATION # MAGIC # WEAKTOSTRONG # SUPERPOWERS # OVERPOWERED # TRANSMIGRATION # CULTIVATION",
      "genres": [
        "Web Novel"
      ],
      "metadata": {
        "ranking_page": "https://www.webnovel.com/ranking/novel/season/best_sellers"
      },
      "previous_score": null,
      "velocity": null
    },
    {
      "id": "goodnovel-book-Ex-Husband-s-Regret_31000657155",
      "title": "Ex-Husband's Regret",
      "source": "GoodNovel",
      "category": "romance",
      "score": 13.0,
      "url": "https://www.goodnovel.com/book/Ex-Husband-s-Regret_31000657155",
      "image": "https://acf.goodnovel.com/book/202309/Ex-Husband-s-Regret/f7c3f3b5a311ea1b6324681fe244b3576ab84ba66839667827ebd33e879a567e.jpg?v=1&p=1&w=1080&a=webp",
      "description": "Ava: Nine years ago I did something terrible. it wasn't one of my best moments but I saw an opportunity to have the guy I've loved since I was a young girl and I took it. Fast forward to years later and I'm tired of living in a loveless marriage. I want to free both of us from a marriage that should never have taken place. They say if you love something.... It was time to let him go. I know he'll never love me and that I'll never be his choice. His heart will always belong to Her and despite my sins, I deserve to be loved.Rowan: Nine years ago, I was so in love I could barely see right. I ruined it when I made the worst mistake of my life and in the process I lost the love of my life. I knew I had to step up in my responsibility and so I did, with an unwanted wife. With the wrong woman. Now she has once again flipped my life by divorcing me. To make matters even more complicated, the love of my life is back in town. Now the only question is, who is the right woman? Is it the girl I fell head over heels in love with years ago? or is it my ex wife, the woman I never wanted but had to marry?",
      "genres": [
        "Romance"
      ],
      "metadata": {
        "ranking_page": "https://www.goodnovel.com/"
      },
      "previous_score": null,
      "velocity": null
    },
    {
      "id": "goodnovel-book-The-CEO-s-Contractual-Wife_31001104597",
      "title": "The CEO's Contractual Wife",
      "source": "GoodNovel",
      "category": "romance",
      "score": 12.0,
      "url": "https://www.goodnovel.com/book/The-CEO-s-Contractual-Wife_31001104597",
      "image": "https://acf.goodnovel.com/book/202508/239f7a021b82982bc291f9c5dffdff43990cb0e2ba0a26eea7687a26fd8825b1.jpg?v=1&p=1&w=1080&a=webp",
      "description": "Olivia Morgan’s world is turned upside down when she walks in on her boyfriend betraying her with her friend. Devastated and drowning in debt, she’s thrust into an unlikely arrangement with Alexander Carter, the cold and calculating CEO of Carter Enterprises. In exchange for a year-long marriage of convenience, Olivia receives the money she desperately needs—and a promotion she never expected. But as their fake relationship blurs the lines between business and pleasure, Olivia finds herself torn between the man who offers her everything and the business rival who wants her heart. In a world where betrayal is just a step away and desire burns hot, Olivia must navigate her emotions, her career, and a dangerous game of power, passion, and secrets. Can she keep her heart guarded while falling deeper into a billionaire’s web of lust and love? Or will Alexander’s cold heart melt in the heat of their undeniable chemistry?",
      "genres": [
        "Romance"
      ],
      "metadata": {
        "ranking_page": "https://www.goodnovel.com/"
      },
      "previous_score": null,
      "velocity": null
    },
    {
      "id": "goodnovel-book-Tattooed-Luna_31000656745",
      "title": "Tattooed Luna",
      "source": "GoodNovel",
      "category": "romance",
      "score": 11.0,
      "url": "https://www.goodnovel.com/book/Tattooed-Luna_31000656745",
      "image": "https://acf.goodnovel.com/book/202310/Tattooed-Luna/0e76d14b6ddb45599d60aa3975e063fea6913b5007f8abc4a2e2c6285319f5fd.jpg?v=1&p=1&w=1080&a=webp",
      "description": "*There are three books in one! Since they need to be read in order, they are one right after another! * \n\nWith a genius IQ and her own tattoo shop, Kristen is about to become 18. After years of being abused by her stepmother, Kristen has decided to leave her pack with the money her tattoo shop has made. Regardless of who her mate is, Kristen will be on her own adventure. \n\nUnfortunately, more than one male has a problem with her independence. Kristen's fiery personality has placed her into a situation that is forcing her to face everything she has escaped. How much can one person endure before they give up?",
      "genres": [
        "Romance"
      ],
      "metadata": {
        "ranking_page": "https://www.goodnovel.com/"
      },
      "previous_score": null,
      "velocity": null
    },
    {
      "id": "webnovel-book-the-heroines-can-hear-my-and-the-protagonist%E2%80%99s-inner-voice!_35792820500281205",
      "title": "The Heroines Can Hear My and the Protagonist’s Inner Voice!?",
      "source": "WebNovel",
      "category": "web_novel",
      "score": 2.0,
      "url": "https://www.webnovel.com/book/the-heroines-can-hear-my-and-the-protagonist%E2%80%99s-inner-voice!_35792820500281205",
      "image": "https://book-pic.webnovel.com/bookcover/35792820500281205?imageMogr2/thumbnail/600x&imageId=1781260011284",
      "description": "# ACTION # ROMANCE # ADVENTURE # SYSTEM # R18 # COMEDY # HAREM # TRANSMIGRATION # SLICEOFLIFE # VILLAIN",
      "genres": [
        "Web Novel"
      ],
      "metadata": {
        "ranking_page": "https://www.webnovel.com/ranking/novel/season/best_sellers"
      },
      "previous_score": null,
      "velocity": null
    },
    {
      "id": "goodnovel-book-The-Alpha-King-s-Possession_31000225606",
      "title": "The Alpha King's Possession",
      "source": "GoodNovel",
      "category": "romance",
      "score": 2.0,
      "url": "https://www.goodnovel.com/book/The-Alpha-King-s-Possession_31000225606",
      "image": "https://acf.goodnovel.com/book/202206/ed5b182732b042c6204fabee8cad12612fa80c5149ad069557818570f134c036.jpg?v=1&p=1&w=1080&a=webp",
      "description": "The Alpha King's Possession  is a Werewolf novel written by Moonlight Muse that covers Fast-Paced Plot, Steamy, Dark Romance. Read full chapters of this story online on GoodNovel.",
      "genres": [
        "Romance"
      ],
      "metadata": {
        "ranking_page": "https://www.goodnovel.com/"
      },
      "previous_score": null,
      "velocity": null
    }
  ]
}