{
  "generated_at_utc": "2026-06-18T03:36:29Z",
  "date": "2026-06-18",
  "item_count": 75,
  "errors": [
    {
      "provider": "jikan_season_now",
      "error": "504 Server Error: Gateway Time-out for url: https://api.jikan.moe/v4/seasons/now?limit=15"
    },
    {
      "provider": "jikan_top_manga",
      "error": "504 Server Error: Gateway Time-out for url: https://api.jikan.moe/v4/top/manga?limit=15"
    },
    {
      "provider": "jikan_top_novels",
      "error": "504 Server Error: Gateway Time-out for url: https://api.jikan.moe/v4/top/manga?limit=15&type=lightnovels"
    },
    {
      "provider": "reddit_discussed",
      "error": "403 Client Error: Blocked for url: https://www.reddit.com/r/manhwa/hot.json?limit=15"
    }
  ],
  "items": [
    {
      "id": "webnovel-book-the-heroines-can-hear-my-and-the-protagonist%E2%80%99s-inner-voice!_35792820500281205",
      "title": "The Heroines Can Hear My and the Protagonist’s Inner Voice!?",
      "source": "WebNovel",
      "category": "web_novel",
      "score": 6.0,
      "url": "https://www.webnovel.com/book/the-heroines-can-hear-my-and-the-protagonist%E2%80%99s-inner-voice!_35792820500281205",
      "image": "https://book-pic.webnovel.com/bookcover/35792820500281205?imageMogr2/thumbnail/600x&imageId=1781260011284",
      "description": "# ACTION # ROMANCE # ADVENTURE # SYSTEM # R18 # COMEDY # HAREM # TRANSMIGRATION # SLICEOFLIFE # VILLAIN",
      "genres": [
        "Web Novel"
      ],
      "metadata": {
        "ranking_page": "https://www.webnovel.com/ranking/novel/season/best_sellers"
      },
      "previous_score": 2.0,
      "velocity": 2.0
    },
    {
      "id": "webnovel-book-my-apocalypse-system-arrives-10-years-early_35233954100293305",
      "title": "My Apocalypse System Arrives 10 Years Early",
      "source": "WebNovel",
      "category": "web_novel",
      "score": 7.0,
      "url": "https://www.webnovel.com/book/my-apocalypse-system-arrives-10-years-early_35233954100293305",
      "image": "https://book-pic.webnovel.com/bookcover/35233954100293305?imageMogr2/thumbnail/600x&imageId=1776306636823",
      "description": "# SYSTEM # KINGDOMBUILDING",
      "genres": [
        "Web Novel"
      ],
      "metadata": {
        "ranking_page": "https://www.webnovel.com/ranking/novel/season/best_sellers"
      },
      "previous_score": 3.0,
      "velocity": 1.3333333333333333
    },
    {
      "id": "webnovel-book-gacha-harem-system_35385385708000905",
      "title": "Gacha Harem System",
      "source": "WebNovel",
      "category": "web_novel",
      "score": 9.0,
      "url": "https://www.webnovel.com/book/gacha-harem-system_35385385708000905",
      "image": "https://book-pic.webnovel.com/bookcover/35385385708000905?imageMogr2/thumbnail/600x&imageId=1781541166055",
      "description": "# ACTION # ROMANCE # ADVENTURE # SYSTEM # R18 # COMEDY # HAREM # OVERPOWERED # TRANSMIGRATION # SLICEOFLIFE",
      "genres": [
        "Web Novel"
      ],
      "metadata": {
        "ranking_page": "https://www.webnovel.com/ranking/novel/season/best_sellers"
      },
      "previous_score": 4.0,
      "velocity": 1.25
    },
    {
      "id": "webnovel-book-her-food-livestream-broke-the-galaxy_34992979700618405",
      "title": "Her Food Livestream Broke the Galaxy",
      "source": "WebNovel",
      "category": "web_novel",
      "score": 8.0,
      "url": "https://www.webnovel.com/book/her-food-livestream-broke-the-galaxy_34992979700618405",
      "image": "https://book-pic.webnovel.com/bookcover/34992979700618405?imageMogr2/thumbnail/600x&imageId=1775183955367",
      "description": "# WEAKTOSTRONG # STRONGFL # SUPERSTAR # SPACE # FEELINGGOOD # GOURMET",
      "genres": [
        "Web Novel"
      ],
      "metadata": {
        "ranking_page": "https://www.webnovel.com/ranking/novel/season/best_sellers"
      },
      "previous_score": 5.0,
      "velocity": 0.6
    },
    {
      "id": "goodnovel-book-The-CEO-s-Contractual-Wife_31001104597",
      "title": "The CEO's Contractual Wife",
      "source": "GoodNovel",
      "category": "romance",
      "score": 16.0,
      "url": "https://www.goodnovel.com/book/The-CEO-s-Contractual-Wife_31001104597",
      "image": "https://acf.goodnovel.com/book/202508/239f7a021b82982bc291f9c5dffdff43990cb0e2ba0a26eea7687a26fd8825b1.jpg?v=1&p=1&w=1080&a=webp",
      "description": "Olivia Morgan’s world is turned upside down when she walks in on her boyfriend betraying her with her friend. Devastated and drowning in debt, she’s thrust into an unlikely arrangement with Alexander Carter, the cold and calculating CEO of Carter Enterprises. In exchange for a year-long marriage of convenience, Olivia receives the money she desperately needs—and a promotion she never expected. But as their fake relationship blurs the lines between business and pleasure, Olivia finds herself torn between the man who offers her everything and the business rival who wants her heart. In a world where betrayal is just a step away and desire burns hot, Olivia must navigate her emotions, her career, and a dangerous game of power, passion, and secrets. Can she keep her heart guarded while falling deeper into a billionaire’s web of lust and love? Or will Alexander’s cold heart melt in the heat of their undeniable chemistry?",
      "genres": [
        "Romance"
      ],
      "metadata": {
        "ranking_page": "https://www.goodnovel.com/"
      },
      "previous_score": 12.0,
      "velocity": 0.3333333333333333
    },
    {
      "id": "webnovel-book-working-in-a-zoo-with-beast-taming-system_35475348608544705",
      "title": "Working in a Zoo with Beast Taming System",
      "source": "WebNovel",
      "category": "web_novel",
      "score": 11.0,
      "url": "https://www.webnovel.com/book/working-in-a-zoo-with-beast-taming-system_35475348608544705",
      "image": "https://book-pic.webnovel.com/bookcover/35475348608544705?imageMogr2/thumbnail/600x&imageId=1778641179571",
      "description": "# SYSTEM # BEAST TAMING",
      "genres": [
        "Web Novel"
      ],
      "metadata": {
        "ranking_page": "https://www.webnovel.com/ranking/novel/season/best_sellers"
      },
      "previous_score": 10.0,
      "velocity": 0.1
    },
    {
      "id": "webnovel-book-last-born-of-the-desdemona_35438027108926505",
      "title": "Last Born Of The Desdemona",
      "source": "WebNovel",
      "category": "web_novel",
      "score": 13.0,
      "url": "https://www.webnovel.com/book/last-born-of-the-desdemona_35438027108926505",
      "image": "https://book-pic.webnovel.com/bookcover/35438027108926505?imageMogr2/thumbnail/600x&imageId=1774464813616",
      "description": "# ACTION # ROMANCE # ADVENTURE # SYSTEM # REINCARNATION # R18 # OVERPOWERED # VILLAIN # EVOLUTION # YANDERE",
      "genres": [
        "Web Novel"
      ],
      "metadata": {
        "ranking_page": "https://www.webnovel.com/ranking/novel/season/best_sellers"
      },
      "previous_score": 12.0,
      "velocity": 0.08333333333333333
    },
    {
      "id": "anilist-anime-194393",
      "title": "I Want to End this Love Game",
      "source": "AniList",
      "category": "anime",
      "score": 42937.0,
      "url": "https://anilist.co/anime/194393",
      "image": "https://s4.anilist.co/file/anilistcdn/media/anime/cover/large/bx194393-0H9yYABu6y0i.jpg",
      "description": "Childhood friends Yukiya and Miku share everything…except their feelings. Ever since sixth grade, they’ve played a “love game”: they take turns saying “I love you” and whoever gets flustered first loses. Now in high school, their hearts are closer than ever—but will they finally find the courage to confess?\n<br><br>\n(Source: Crunchyroll)",
      "genres": [
        "Comedy",
        "Romance"
      ],
      "metadata": {
        "average_score": 73
      },
      "previous_score": 42470.0,
      "velocity": 0.0109959971744761
    },
    {
      "id": "anilist-anime-169580",
      "title": "I Made Friends with the Second Prettiest Girl in My Class",
      "source": "AniList",
      "category": "anime",
      "score": 73450.0,
      "url": "https://anilist.co/anime/169580",
      "image": "https://s4.anilist.co/file/anilistcdn/media/anime/cover/large/bx169580-nXxpmqu6UVux.jpg",
      "description": "Maki Maehara, the class outcast, finally makes his first friend: Umi Asanagi, the second-prettiest girl in class and the center of everyone’s attention. He’s convinced she’s out of his league, but as their unlikely friendship grows, Maki starts to wonder…could there be more than just friendship between them?<br>\n<br>\n(Source: Crunchyroll)",
      "genres": [
        "Comedy",
        "Romance"
      ],
      "metadata": {
        "average_score": 80
      },
      "previous_score": 72712.0,
      "velocity": 0.010149631422598745
    },
    {
      "id": "anilist-anime-199547",
      "title": "MARRIAGETOXIN",
      "source": "AniList",
      "category": "anime",
      "score": 68088.0,
      "url": "https://anilist.co/anime/199547",
      "image": "https://s4.anilist.co/file/anilistcdn/media/anime/cover/large/bx199547-LAaG3cmKCGhr.jpg",
      "description": "For centuries, the deadly arts have been perfected by those known as the Masters.\nAmong them, the Poison Masters of the Five Great Families hold the most fearsome power and influence. \nHikaru Gero, heir to the Poison Masters’ Gero Family, has lived his entire life in the underworld, far removed from love or marriage.\nBut when the Gero Family head decrees that Hikaru’s sister must bear an heir to preserve the bloodline—by force if necessary—Hikaru resolves to protect her at all costs.\nIt is then that Hikaru encounters Mei Kinosaki, a brilliant marriage swindler who becomes the target of his latest job.\nRealizing that the only way of solving the family succession problem and protecting his sister is through marriage, Hikaru impulsively asks Mei for help in finding a bride.\n<br><br>\n(Source: EMOTION Label Channel)",
      "genres": [
        "Action",
        "Comedy",
        "Drama",
        "Romance"
      ],
      "metadata": {
        "average_score": 75
      },
      "previous_score": 67521.0,
      "velocity": 0.008397387479450838
    },
    {
      "id": "anilist-anime-147105",
      "title": "Witch Hat Atelier",
      "source": "AniList",
      "category": "anime",
      "score": 179142.0,
      "url": "https://anilist.co/anime/147105",
      "image": "https://s4.anilist.co/file/anilistcdn/media/anime/cover/large/bx147105-rwOX8qyUy8gV.jpg",
      "description": "In a world where everyone takes wonders like magic spells and dragons for granted, Coco is a girl with a simple dream: she wants to be a witch. But everybody knows magicians are born, not made, and Coco was not born with a gift for magic. Resigned to her un-magical life, Coco is about to give up on her dream to become a witch … until the day she meets Qifrey, a mysterious, traveling magician. After secretly seeing Qifrey perform magic in a way she’s never seen before, Coco soon learns what everybody “knows” might not be the truth, and discovers that her magical dream may not be as far away as it may seem... <br>\n<br>\n(Source: Kodansha USA) <br><br>\n\n<i>Note: Tongari Boushi no Atelier episode 2 was streamed a week in advance on Crunchyroll, ABEMA, and Netflix, alongside episode 1. Streaming is one week ahead of the TV broadcast.</i>",
      "genres": [
        "Adventure",
        "Drama",
        "Fantasy"
      ],
      "metadata": {
        "average_score": 86
      },
      "previous_score": 178167.0,
      "velocity": 0.005472393877654111
    },
    {
      "id": "anilist-anime-182300",
      "title": "Wistoria: Wand and Sword Season 2",
      "source": "AniList",
      "category": "anime",
      "score": 93046.0,
      "url": "https://anilist.co/anime/182300",
      "image": "https://s4.anilist.co/file/anilistcdn/media/anime/cover/large/bx182300-IYkq5KrkQq1V.jpg",
      "description": "The second season of <i>Tsue to Tsurugi no Wistoria</i>.<br><br>\nWill, a washout student at a magical academy who is unable to use magic, is aiming to join the top tier of mages, the Magia Vander, to fulfill a promise to his childhood friend, Elfaria. Wielding a sword instead of a wand, his abilities are slowly recognized within the academy. During the all-student praxis dungeon training he undertakes with Lihanna and the other top students of his year, they are ambushed by a mysterious mage. Though they barely manage to survive the attack together, they go on to face the exit exam. Can Will reach the girl waiting for him in the tower?<br><br>\n(Source: Official Site)",
      "genres": [
        "Action",
        "Adventure",
        "Drama",
        "Fantasy"
      ],
      "metadata": {
        "average_score": 82
      },
      "previous_score": 92559.0,
      "velocity": 0.005261508875420003
    },
    {
      "id": "anilist-anime-195600",
      "title": "Daemons of the Shadow Realm",
      "source": "AniList",
      "category": "anime",
      "score": 104537.0,
      "url": "https://anilist.co/anime/195600",
      "image": "https://s4.anilist.co/file/anilistcdn/media/anime/cover/large/bx195600-moI0UFArtOme.jpg",
      "description": "In a remote mountain village under the watchful eyes of two stone guardians, the young Yuru contentedly lives off the land while staying close to the only family he has left—Asa, his precious twin sister. Asa, meanwhile, carries out a mysterious “duty” on behalf of the village while locked in a cage. Why is Asa a prisoner? And what other secrets does Yuru’s otherwise idyllic home hide?\n<br><br>(Source: Square Enix)",
      "genres": [
        "Action",
        "Adventure",
        "Comedy",
        "Fantasy",
        "Supernatural"
      ],
      "metadata": {
        "average_score": 78
      },
      "previous_score": 104096.0,
      "velocity": 0.004236474023977866
    },
    {
      "id": "anilist-anime-189046",
      "title": "Re:ZERO -Starting Life in Another World- Season 4",
      "source": "AniList",
      "category": "anime",
      "score": 108677.0,
      "url": "https://anilist.co/anime/189046",
      "image": "https://s4.anilist.co/file/anilistcdn/media/anime/cover/large/bx189046-yaHWtS5FII46.jpg",
      "description": "The fourth season of <i>Re:Zero kara Hajimeru Isekai Seikatsu</i>.<br><br>\n\nTo save his stricken allies, Subaru faces a deadly desert to find the Sage at Pleiades Watchtower.<br><br>\n\n(Source: Crunchyroll News)\n\n<br><br>\n<i>Note: Episode 1 pre-screened at Lucca Comics & Games on November 1, 2025, before the Japanese television broadcast.",
      "genres": [
        "Action",
        "Adventure",
        "Drama",
        "Fantasy",
        "Psychological",
        "Romance",
        "Thriller"
      ],
      "metadata": {
        "average_score": 88
      },
      "previous_score": 108302.0,
      "velocity": 0.003462539934627246
    },
    {
      "id": "anilist-anime-180745",
      "title": "Classroom of the Elite 4th Season: Second Year, First Semester",
      "source": "AniList",
      "category": "anime",
      "score": 98174.0,
      "url": "https://anilist.co/anime/180745",
      "image": "https://s4.anilist.co/file/anilistcdn/media/anime/cover/large/bx180745-OEZaBeEdWozn.png",
      "description": "The fourth season of <i> Youkoso Jitsuryoku Shijou Shugi no Kyoushitsu e</i>.<br><br>\nAs Ayanokouji and his classmates begin their second year at the Advanced Nurturing High School, they’re greeted by a fresh gauntlet of exams and a fresh batch of rather unique first-year students. They’ll have to get to know each other quickly, because the first special exam pairs the first-years with the second-years on a written test—with only the second-years facing expulsion if their team performs poorly! Worse yet? It seems one of the new first-years is also from the White Room. Can Ayanokouji avoid expulsion while sussing out the identity of this hidden foe?\n<br><br>\n(Source: Seven Seas)",
      "genres": [
        "Drama",
        "Psychological"
      ],
      "metadata": {
        "average_score": 78
      },
      "previous_score": 97896.0,
      "velocity": 0.002839748304322955
    },
    {
      "id": "anilist-manga-182066",
      "title": "The Regressed Mercenary Has a Plan",
      "source": "AniList",
      "category": "manhwa",
      "score": 20393.0,
      "url": "https://anilist.co/manga/182066",
      "image": "https://s4.anilist.co/file/anilistcdn/media/manga/cover/large/bx182066-kqOV7WW1DAH4.jpg",
      "description": "Cecil Perdium, the Mercenary King, was killed in battle before he could avenge his family. As he faces death, he learns that Duke Delphine, the man who caused the downfall of his family, didn't work alone. Suddenly waking up as his teenage self, Cecil must work to both overcome his poor reputation and build up his strength to save his family. With their soldiers and knights defecting due to the harsh conditions they must endure, he has his work cut out for him. Can Cecil become the mighty warrior he once was and avert his family's fate?\n<br><br>\n(Source: WEBTOON)",
      "genres": [
        "Action",
        "Fantasy"
      ],
      "metadata": {
        "average_score": 80,
        "country_of_origin": "KR",
        "format": "MANGA"
      },
      "previous_score": 20359.0,
      "velocity": 0.0016700230856132423
    },
    {
      "id": "anilist-manga-170400",
      "title": "The Stellar Swordmaster",
      "source": "AniList",
      "category": "manhwa",
      "score": 27500.0,
      "url": "https://anilist.co/manga/170400",
      "image": "https://s4.anilist.co/file/anilistcdn/media/manga/cover/large/bx170400-yMIuOIboWuoO.jpg",
      "description": "The so-called “Lighthouse of the North,” the prosperous trading town of Schoarra, hides a dark underbelly: seedy slums ruled by five ruthless crime bosses. When streetwise orphan Vlad finds the brothel he works for decimated by a disgraced knight, he turns to the path of the blade, pledging himself to the pursuit of power by sword. Blessed with the ability to seek wisdom from his sentient sword, Vlad embarks upon a journey of growth and peril as swordsman in service to the powerful House Vayezid.<br>\n<br>\n(Source: WEBTOON)",
      "genres": [
        "Action",
        "Adventure",
        "Fantasy"
      ],
      "metadata": {
        "average_score": 82,
        "country_of_origin": "KR",
        "format": "MANGA"
      },
      "previous_score": 27463.0,
      "velocity": 0.0013472672322761535
    },
    {
      "id": "anilist-anime-269",
      "title": "Bleach",
      "source": "AniList",
      "category": "anime",
      "score": 489933.0,
      "url": "https://anilist.co/anime/269",
      "image": "https://s4.anilist.co/file/anilistcdn/media/anime/cover/large/bx269-d2GmRkJbMopq.png",
      "description": "Ichigo Kurosaki is a rather normal high school student apart from the fact he has the ability to see ghosts. This ability never impacted his life in a major way until the day he encounters the Shinigami Kuchiki Rukia, who saves him and his family's lives from a Hollow, a corrupt spirit that devours human souls. \n<br><br>\nWounded during the fight against the Hollow, Rukia chooses the only option available to defeat the monster and passes her Shinigami powers to Ichigo. Now forced to act as a substitute until Rukia recovers, Ichigo hunts down the Hollows that plague his town. \n\n\n",
      "genres": [
        "Action",
        "Adventure",
        "Supernatural"
      ],
      "metadata": {
        "average_score": 79
      },
      "previous_score": 489582.0,
      "velocity": 0.0007169381227251002
    },
    {
      "id": "anilist-manga-106130",
      "title": "Blue Lock",
      "source": "AniList",
      "category": "manga",
      "score": 119183.0,
      "url": "https://anilist.co/manga/106130",
      "image": "https://s4.anilist.co/file/anilistcdn/media/manga/cover/large/bx106130-yPNeuSu75ey1.jpg",
      "description": "After a disastrous defeat at the 2018 World Cup, Japan's team struggles to regroup. But what's missing? An absolute Ace Striker, who can guide them to the win. The Japan Football Union is hell-bent on creating a striker who hungers for goals and thirsts for victory, and who can be the decisive instrument in turning around a losing match...and to do so, they've gathered 300 of Japan's best and brightest youth players. Who will emerge to lead the team...and will they be able to out-muscle and out-ego everyone who stands in their way?\n<br><br>\n(Source: Kodansha USA)\n<br><br>\n<i>Note: Winner of the 45th Kodansha Manga Award in the Shounen Category in 2021.</i>",
      "genres": [
        "Action",
        "Drama",
        "Sports"
      ],
      "metadata": {
        "average_score": 82,
        "country_of_origin": "JP",
        "format": "MANGA"
      },
      "previous_score": 119101.0,
      "velocity": 0.0006884912805098194
    },
    {
      "id": "anilist-anime-21",
      "title": "ONE PIECE",
      "source": "AniList",
      "category": "anime",
      "score": 716310.0,
      "url": "https://anilist.co/anime/21",
      "image": "https://s4.anilist.co/file/anilistcdn/media/anime/cover/large/bx21-ELSYx3yMPcKM.jpg",
      "description": "Gold Roger was known as the Pirate King, the strongest and most infamous being to have sailed the Grand Line. The capture and death of Roger by the World Government brought a change throughout the world. His last words before his death revealed the location of the greatest treasure in the world, One Piece. It was this revelation that brought about the Grand Age of Pirates, men who dreamed of finding One Piece (which promises an unlimited amount of riches and fame), and quite possibly the most coveted of titles for the person who found it, the title of the Pirate King.<br><br>\nEnter Monkey D. Luffy, a 17-year-old boy that defies your standard definition of a pirate. Rather than the popular persona of a wicked, hardened, toothless pirate who ransacks villages for fun, Luffy’s reason for being a pirate is one of pure wonder; the thought of an exciting adventure and meeting new and intriguing people, along with finding One Piece, are his reasons of becoming a pirate. Following in the footsteps of his childhood hero, Luffy and his crew travel across the Grand Line, experiencing crazy adventures, unveiling dark mysteries and battling strong enemies, all in order to reach One Piece.<br><br>\n<b>*This includes the following special episodes:</b><br>\n- Chopperman to the Rescue! Protect the TV Station by the Shore! (Episode 336)<br>\n- The Strongest Tag-Team! Luffy and Toriko's Hard Struggle! (Episode 492)<br>\n- Team Formation! Save Chopper (Episode 542)<br>\n- History's Strongest Collaboration vs. Glutton of the Sea (Episode 590)<br>\n- 20th Anniversary! Special Romance Dawn (Episode 907)",
      "genres": [
        "Action",
        "Adventure",
        "Comedy",
        "Drama",
        "Fantasy"
      ],
      "metadata": {
        "average_score": 87
      },
      "previous_score": 715898.0,
      "velocity": 0.0005755009791897728
    },
    {
      "id": "webnovel-book-the-scumbag%E2%80%99s-guide-to-heroism_35677809208460505",
      "title": "The Scumbag’s Guide To Heroism",
      "source": "WebNovel",
      "category": "web_novel",
      "score": 16.0,
      "url": "https://www.webnovel.com/book/the-scumbag%E2%80%99s-guide-to-heroism_35677809208460505",
      "image": "https://book-pic.webnovel.com/bookcover/35677809208460505?imageMogr2/thumbnail/600x&imageId=1780246597505",
      "description": "# ACTION # ROMANCE # SYSTEM # R18 # WEAKTOSTRONG # SUPERPOWERS # SLICEOFLIFE # SMUT # ACADEMY # ECCHI",
      "genres": [
        "Web Novel"
      ],
      "metadata": {
        "ranking_page": "https://www.webnovel.com/ranking/novel/season/best_sellers"
      },
      "previous_score": 16.0,
      "velocity": 0.0
    },
    {
      "id": "dreame-1646404864",
      "title": "True Luna",
      "source": "Dreame",
      "category": "romance",
      "score": 16.0,
      "url": "https://www.dreame.com/story/1646404864",
      "image": "https://files.dreame.com/images/2023/03/12/1635059837492846592640e5fc146a99.png@208w_300h_2e_53287592837a",
      "description": "I wanted to run to him, but I stopped myself when I saw how cold his stare was. What was going on?",
      "genres": [
        "Fantasy"
      ],
      "metadata": {
        "bid": 1646404864
      },
      "previous_score": 16.0,
      "velocity": 0.0
    },
    {
      "id": "webnovel-book-greymoor-academy-i-accidentally-bonded-with-four-lycan-royals!_35396013508215305",
      "title": "Greymoor Academy: I Accidentally Bonded With Four Lycan Royals!",
      "source": "WebNovel",
      "category": "web_novel",
      "score": 15.0,
      "url": "https://www.webnovel.com/book/greymoor-academy-i-accidentally-bonded-with-four-lycan-royals!_35396013508215305",
      "image": "https://book-pic.webnovel.com/bookcover/35396013508215305?imageMogr2/thumbnail/600x&imageId=1774058219314",
      "description": "# REVENGE # CAMPUS # WEREWOLF # LOVETRIANGLE # ENEMIESTOLOVERS # FATEDLOVE # FORBIDDENLOVE # ABUSEDFL # REJECTED # REVERSE HAREM",
      "genres": [
        "Web Novel"
      ],
      "metadata": {
        "ranking_page": "https://www.webnovel.com/ranking/novel/season/best_sellers"
      },
      "previous_score": 15.0,
      "velocity": 0.0
    },
    {
      "id": "dreame-1231429376",
      "title": "Her Triplet Alphas",
      "source": "Dreame",
      "category": "romance",
      "score": 15.0,
      "url": "https://www.dreame.com/story/1231429376",
      "image": "https://files.dreame.com/images/2020/11/09/13256427573642977285fa8b8a5add51.png@208w_300h_2e_53287592837a",
      "description": "I had never even had one boyfriend, now I had 3 mates?!",
      "genres": [
        "Paranormal"
      ],
      "metadata": {
        "bid": 1231429376
      },
      "previous_score": 15.0,
      "velocity": 0.0
    },
    {
      "id": "webnovel-book-betrayed-by-my-ex-marked-by-his-alpha-emperor-brother_35393754900224005",
      "title": "Betrayed by My Ex, Marked by His Alpha Emperor Brother",
      "source": "WebNovel",
      "category": "web_novel",
      "score": 14.0,
      "url": "https://www.webnovel.com/book/betrayed-by-my-ex-marked-by-his-alpha-emperor-brother_35393754900224005",
      "image": "https://book-pic.webnovel.com/bookcover/35393754900224005?imageMogr2/thumbnail/600x&imageId=1773995997681",
      "description": "# ROMANCE # R18 # WEAKTOSTRONG # WEREWOLF # HISTORICAL # ALPHA # ONENIGHTSTAND # FATEDMATE # BETRAYED",
      "genres": [
        "Web Novel"
      ],
      "metadata": {
        "ranking_page": "https://www.webnovel.com/ranking/novel/season/best_sellers"
      },
      "previous_score": 14.0,
      "velocity": 0.0
    },
    {
      "id": "dreame-742663424",
      "title": "The Rejected Luna's Prince",
      "source": "Dreame",
      "category": "romance",
      "score": 14.0,
      "url": "https://www.dreame.com/story/742663424",
      "image": "https://assets.dreame.com/cover/2024/07/01/180772480422979174466828689f1651.png",
      "description": "That day he made me his in every way possible...But I ended up with pregnant and rejected.",
      "genres": [
        "Romance"
      ],
      "metadata": {
        "bid": 742663424
      },
      "previous_score": 14.0,
      "velocity": 0.0
    },
    {
      "id": "dreame-2880119808",
      "title": "The Defiant Mate",
      "source": "Dreame",
      "category": "romance",
      "score": 13.0,
      "url": "https://www.dreame.com/story/2880119808",
      "image": "https://assets.dreame.com/cover/2024/08/08/182147560613974835266b48cf860d3d.png",
      "description": "I'm pregnant?! No, moon goddess, no! PREGNANCY TEST:POSITIVE  RESULT: 3 WEEKS PREGNANT",
      "genres": [
        "Fantasy"
      ],
      "metadata": {
        "bid": 2880119808
      },
      "previous_score": 13.0,
      "velocity": 0.0
    },
    {
      "id": "dreame-1570579456",
      "title": "The Rejected Wolf",
      "source": "Dreame",
      "category": "romance",
      "score": 12.0,
      "url": "https://www.dreame.com/story/1570579456",
      "image": "https://files.dreame.com/images/2022/07/05/154421336222391910462c3e062ed4c0.png@208w_300h_2e_53287592837a",
      "description": "Her mate rejected her when she fell pregnant with his child.",
      "genres": [
        "Paranormal"
      ],
      "metadata": {
        "bid": 1570579456
      },
      "previous_score": 12.0,
      "velocity": 0.0
    },
    {
      "id": "dreame-20390912",
      "title": "The Unwanted Bride Of Atticus Fawn",
      "source": "Dreame",
      "category": "romance",
      "score": 11.0,
      "url": "https://www.dreame.com/story/20390912",
      "image": "https://files.dreame.com/images/2022/07/22/155038237210369638462da51b8f3dcf.png@208w_300h_2e_53287592837a",
      "description": "And he didn't know how much I loved him. I've hidden it well.",
      "genres": [
        "Romance"
      ],
      "metadata": {
        "bid": 20390912
      },
      "previous_score": 11.0,
      "velocity": 0.0
    },
    {
      "id": "dreame-1411916544",
      "title": "Her Inner Power",
      "source": "Dreame",
      "category": "romance",
      "score": 10.0,
      "url": "https://www.dreame.com/story/1411916544",
      "image": "https://files.dreame.com/images/2022/06/22/153945276692854784062b28ebbe8bae.png@208w_300h_2e_53287592837a",
      "description": "Her soulmate is also her biggest enemy. What will she do?",
      "genres": [
        "Paranormal"
      ],
      "metadata": {
        "bid": 1411916544
      },
      "previous_score": 10.0,
      "velocity": 0.0
    },
    {
      "id": "goodnovel-book-The-Heartless-Alpha-s-Beloved-Luna_31001165452",
      "title": "The Heartless Alpha’s Beloved Luna",
      "source": "GoodNovel",
      "category": "romance",
      "score": 10.0,
      "url": "https://www.goodnovel.com/book/The-Heartless-Alpha-s-Beloved-Luna_31001165452",
      "image": "https://acf.goodnovel.com/book/202601/a89c920a786d425d24ace4a803166207a0985f570cc32829eb7b2c3ecda81927.jpg?v=1&p=1&w=1080&a=webp",
      "description": "Avery watched her boyfriend Ryan cheating with her half sister Zara right in front of her eyes on the Mating Day, the day she was meant to be claimed by Ryan as his chosen mate. The worse thing is that Ryan and Zara had the right to do so, because they just found out they were fated mates. Heartbroken, Avery fleed into the forest, only to fell into the arms of a dangerous stranger whose scent triggered her mating heat. Avery believed he was a rogue, so she just wanted one night of forbidden passion in the dark and ran away the next morning without even knowing what he looked like exactly. However, after she got home, she panicked as she found out she was marked by that stranger... Avery's father threatened to kill her if she couldn't secure a husband who could accept her. Just when Avery thought no one would want a marked girl, Alpha Gideon choose her as his bride, and something about him just seemed familiar....",
      "genres": [
        "Romance"
      ],
      "metadata": {
        "ranking_page": "https://www.goodnovel.com/"
      },
      "previous_score": 10.0,
      "velocity": 0.0
    },
    {
      "id": "dreame-1737958400",
      "title": "Surprising the Bully (True Love Series Book 1)",
      "source": "Dreame",
      "category": "romance",
      "score": 9.0,
      "url": "https://www.dreame.com/story/1737958400",
      "image": "https://assets.dreame.com/cover/2025/09/04/196363845830397952068b9bc71a1797.png",
      "description": "This gorgeous lady is that bullied girl? How can‘t I realize before!",
      "genres": [
        "YA&Teenfiction"
      ],
      "metadata": {
        "bid": 1737958400
      },
      "previous_score": 9.0,
      "velocity": 0.0
    },
    {
      "id": "goodnovel-book-Your-Uncle-s-My-Husband-Now-Back-Off-Ex_31001200284",
      "title": "Your Uncle’s My Husband Now—Back Off, Ex!",
      "source": "GoodNovel",
      "category": "romance",
      "score": 9.0,
      "url": "https://www.goodnovel.com/book/Your-Uncle-s-My-Husband-Now-Back-Off-Ex_31001200284",
      "image": "https://acf.goodnovel.com/book/202512/dd9d70146d0aaa2148e999644f7156f157f3e358313156cefe661f8c6e6ada9d.jpg?v=1&p=1&w=1080&a=webp",
      "description": "On their third wedding anniversary, Clark Summer gifted his wife a diamond necklace named \"Love Nyla,\" broadcasting his devotion to the world. But while the public swooned, Nyla sat alone in their empty home, staring at a photo sent by a stranger: her husband’s new secretary, Jordyn, wearing that same necklace, tangled in Clark’s arms.\nFor three years, Nyla had been the perfect, submissive wife. In return, she received betrayal, humiliation from her mother-in-law, and Clark’s sickening justification that his affair was merely a \"physical necessity\" while he still loved her. He believed Nyla was trapped, tethered to him by her father’s astronomical medical bills. He thought she would swallow the insults and raise his mistress's child.\nHe was wrong.\nSelling their mansion, gathering evidence, and delivering irrefutable proof of her infidelity… Nera turned and left, donning a white lab coat instead of an apron, transforming overnight into a top-tier pharmaceutical researcher who had astonished the industry. \nWhen Clark, with belated repentance and red-eyed pleading for her return, saw his icy ex-wife being gently embraced by his uncle Damon, he saw the aloof man before him. The superior man coldly glanced at his nephew, his voice low and dangerous: \"What are you calling 'wife'? Call her 'auntie'.\"",
      "genres": [
        "Romance"
      ],
      "metadata": {
        "ranking_page": "https://www.goodnovel.com/"
      },
      "previous_score": 9.0,
      "velocity": 0.0
    },
    {
      "id": "dreame-3391824640",
      "title": "My Mate is an Omega",
      "source": "Dreame",
      "category": "romance",
      "score": 8.0,
      "url": "https://www.dreame.com/story/3391824640",
      "image": "https://files.dreame.com/images/2022/08/30/1564736567288070144630e8a1b46c5d.png@208w_300h_2e_53287592837a",
      "description": "Can an Omega couple prove how powerful they can become, or will the twists and turns of life tear them apart?",
      "genres": [
        "Romance"
      ],
      "metadata": {
        "bid": 3391824640
      },
      "previous_score": 8.0,
      "velocity": 0.0
    },
    {
      "id": "goodnovel-book-Second-Chance-for-the-Barren-Luna_31001064899",
      "title": "Second Chance for the Barren Luna",
      "source": "GoodNovel",
      "category": "romance",
      "score": 8.0,
      "url": "https://www.goodnovel.com/book/Second-Chance-for-the-Barren-Luna_31001064899",
      "image": "https://acf.goodnovel.com/book/202658/28f6ca955614a0ab96b4d9765d3611118f31a5bb63ad1afd440e89588aa74276.jpg?v=1&p=1&w=1080&a=webp",
      "description": "“If you can’t provide an heir, you’re a Luna in name only. I need more than a worthless, barren omega cosplaying as a Luna!”\n\nMy Alpha husband Jason’s words cut deeper than any silver blade. For three years, I have kept the truth from him. He thinks he married a weak omega. But the truth? I am the Alpha King’s daughter.\n\nI wait eagerly for his return from a victorious war, ready to reveal who I truly am. Only to find him walking back with his mistress, Viki, who has already carrying his pup.\n\n“You have two options,” Jason snarls, eyes cold. “Lose your status as Luna and go back to being a useless omega. Or stay for Viki and help raise my heir.”\n\nPushed to my breaking point, I accept his rejection and return to my father’s kingdom. I think my heart is dead but fate has led me to a dangerous second-chance mate. Worse, Jason can’t let me go that easily.",
      "genres": [
        "Romance"
      ],
      "metadata": {
        "ranking_page": "https://www.goodnovel.com/"
      },
      "previous_score": 8.0,
      "velocity": 0.0
    },
    {
      "id": "dreame-696460032",
      "title": "Seven Days Before Divorce",
      "source": "Dreame",
      "category": "romance",
      "score": 7.0,
      "url": "https://www.dreame.com/story/696460032",
      "image": "https://files.dreame.com/images/2022/06/13/153630161370117324862a717fec55a9.png@208w_300h_2e_53287592837a",
      "description": "\"Ah... Too deep, honey. Cirrus, slow down, you are hurting me.\"“Cirrus? But my name isn’t Cirrus...”",
      "genres": [
        "Romance"
      ],
      "metadata": {
        "bid": 696460032
      },
      "previous_score": 7.0,
      "velocity": 0.0
    },
    {
      "id": "goodnovel-book-His-Plump-Mate_31001222962",
      "title": "His Plump Mate",
      "source": "GoodNovel",
      "category": "romance",
      "score": 7.0,
      "url": "https://www.goodnovel.com/book/His-Plump-Mate_31001222962",
      "image": "https://acf.goodnovel.com/book/202511/1f46a28711a8c933c5db6bdeb2f147a343bbb579207d302aa5a1e5d714ed7fed.jpg?v=1&p=1&w=1080&a=webp",
      "description": "His Plump Mate is a Werewolf novel written by BUCHANAN that covers Werewolf, Steamy, Alpha. Read full chapters of this story online on GoodNovel.",
      "genres": [
        "Romance"
      ],
      "metadata": {
        "ranking_page": "https://www.goodnovel.com/"
      },
      "previous_score": 7.0,
      "velocity": 0.0
    },
    {
      "id": "dreame-1094329344",
      "title": "Big, Bold, And Beautiful.",
      "source": "Dreame",
      "category": "romance",
      "score": 6.0,
      "url": "https://www.dreame.com/story/1094329344",
      "image": "https://files.dreame.com/images/2022/08/04/155507799528128921662eb66dc471a3.png@208w_300h_2e_53287592837a",
      "description": "When pluz-size girl meets her billionaire Alpha",
      "genres": [
        "Romance"
      ],
      "metadata": {
        "bid": 1094329344
      },
      "previous_score": 6.0,
      "velocity": 0.0
    },
    {
      "id": "goodnovel-book-Billionaire-s-Match_31001148338",
      "title": "Billionaire's Match",
      "source": "GoodNovel",
      "category": "romance",
      "score": 6.0,
      "url": "https://www.goodnovel.com/book/Billionaire-s-Match_31001148338",
      "image": "https://acf.goodnovel.com/book/202512/483b3bc53d3d95d1d1dc8e8dc6346c35c2b245d28a13e1e7ee37fc4f31838ff2.jpg?v=1&p=1&w=1080&a=webp",
      "description": "Billionaire's Match is a Romance novel written by Tangy Candy that covers Drama, Fast-Paced Plot, Sweet Love. Read full chapters of this story online on GoodNovel.",
      "genres": [
        "Romance"
      ],
      "metadata": {
        "ranking_page": "https://www.goodnovel.com/"
      },
      "previous_score": 6.0,
      "velocity": 0.0
    },
    {
      "id": "dreame-2235114496",
      "title": "His Silent Temptation",
      "source": "Dreame",
      "category": "romance",
      "score": 5.0,
      "url": "https://www.dreame.com/story/2235114496",
      "image": "https://files.dreame.com/images/2022/07/22/155029417127186841662d9ff94a9af0.png@208w_300h_2e_53287592837a",
      "description": "I’m jealous of your heart pumping inside of you and I’m not",
      "genres": [
        "Romance"
      ],
      "metadata": {
        "bid": 2235114496
      },
      "previous_score": 5.0,
      "velocity": 0.0
    },
    {
      "id": "goodnovel-book-Married-at-First-Sight_31000384431",
      "title": "Married at First Sight",
      "source": "GoodNovel",
      "category": "romance",
      "score": 5.0,
      "url": "https://www.goodnovel.com/book/Married-at-First-Sight_31000384431",
      "image": "https://acf.goodnovel.com/book/202208/Married-at-First-Sight/f0b5eb8152a5c2a3b57c993c0e60c9d94549f934a29d96cbecce2c282d8f4269.jpg?v=1&p=1&w=1080&a=webp",
      "description": "The novel Married at First Sight is a Billionaire, telling a story of Since the day Serenity got hitched to a stranger on their blind date, she had assumed married life would be ordinary but respectful and mundane. It never crossed her mind that her new husband would be clingy like a piece of gum stuck to the bottom of a shoe. To her utmost surprise, he could make... Married at First Sight PDF",
      "genres": [
        "Romance"
      ],
      "metadata": {
        "ranking_page": "https://www.goodnovel.com/"
      },
      "previous_score": 5.0,
      "velocity": 0.0
    },
    {
      "id": "dreame-1317150208",
      "title": "Enslaved By The Alpha",
      "source": "Dreame",
      "category": "romance",
      "score": 4.0,
      "url": "https://www.dreame.com/story/1317150208",
      "image": "https://assets.dreame.com/cover/2023/09/15/170260495091342950465041a0bb531f.png",
      "description": "The woman he had planned to kidnap and kill was his very own mate !",
      "genres": [
        "Paranormal"
      ],
      "metadata": {
        "bid": 1317150208
      },
      "previous_score": 4.0,
      "velocity": 0.0
    },
    {
      "id": "goodnovel-book-CLAIMED-BY-THE-MAFIA-DON_31001293897",
      "title": "CLAIMED BY THE MAFIA DON",
      "source": "GoodNovel",
      "category": "romance",
      "score": 4.0,
      "url": "https://www.goodnovel.com/book/CLAIMED-BY-THE-MAFIA-DON_31001293897",
      "image": "https://acf.goodnovel.com/book/202601/8bf3dc2930c8594b95cb8956fdadcecfe5c1e90e58d4415a32c3435acdd20da5.jpg?v=1&p=1&w=1080&a=webp",
      "description": "CLAIMED BY THE MAFIA DON is a Mafia novel written by JacqueAuthor  that covers Dark Romance, Contemporary, Ruthless. Read full chapters of this story online on GoodNovel.",
      "genres": [
        "Romance"
      ],
      "metadata": {
        "ranking_page": "https://www.goodnovel.com/"
      },
      "previous_score": 4.0,
      "velocity": 0.0
    },
    {
      "id": "dreame-850797312",
      "title": "Sky's Rejection",
      "source": "Dreame",
      "category": "romance",
      "score": 3.0,
      "url": "https://www.dreame.com/story/850797312",
      "image": "https://files.dreame.com/images/2022/01/03/147784537540583014461d26e5a4bdf2.png@208w_300h_2e_53287592837a",
      "description": "Until she met her second chance, the Royal Alpha King",
      "genres": [
        "Paranormal"
      ],
      "metadata": {
        "bid": 850797312
      },
      "previous_score": 3.0,
      "velocity": 0.0
    },
    {
      "id": "goodnovel-book-The-Alpha-s-Unwanted-Luna_31001153954",
      "title": "The Alpha's Unwanted Luna Series",
      "source": "GoodNovel",
      "category": "romance",
      "score": 3.0,
      "url": "https://www.goodnovel.com/book/The-Alpha-s-Unwanted-Luna_31001153954",
      "image": "https://acf.goodnovel.com/book/202640/5cc80cbafb79aa1dd9e17ed34a4586496ee10b9ca1002e466f574941d419d6d6.jpg?v=1&p=1&w=1080&a=webp",
      "description": "The Alpha's Unwanted Luna Series is a Werewolf novel written by Miss L that covers Werewolf, Alpha, Warrior. Read full chapters of this story online on GoodNovel.",
      "genres": [
        "Romance"
      ],
      "metadata": {
        "ranking_page": "https://www.goodnovel.com/"
      },
      "previous_score": 3.0,
      "velocity": 0.0
    },
    {
      "id": "dreame-598367488",
      "title": "Holiday Hockey Tale: The Icebreaker's Impasse",
      "source": "Dreame",
      "category": "romance",
      "score": 2.0,
      "url": "https://www.dreame.com/story/598367488",
      "image": "https://assets.dreame.com/cover/2025/03/21/190312864397959577667dd9a49fe200.png@350w_500h.webp",
      "description": "Luci Forrester is a college senior. She hasn't had the best college experience and is counting down the days to leave the hell that is Kenton University. If she didn't depend on her scholarship, she'd...",
      "genres": [
        "Romance"
      ],
      "metadata": {
        "bid": 598367488
      },
      "previous_score": 2.0,
      "velocity": 0.0
    },
    {
      "id": "webnovel-book-reborn-with-infinite-system-points-i-gathered-all-sss-classes!_35479981708644005",
      "title": "Reborn with Infinite System Points, I Gathered All SSS Classes!",
      "source": "WebNovel",
      "category": "web_novel",
      "score": 12.0,
      "url": "https://www.webnovel.com/book/reborn-with-infinite-system-points-i-gathered-all-sss-classes!_35479981708644005",
      "image": "https://book-pic.webnovel.com/bookcover/35479981708644005?imageMogr2/thumbnail/600x&imageId=1774877509893",
      "description": "# ACTION # ADVENTURE # SYSTEM # REINCARNATION # MAGIC # WEAKTOSTRONG # SUPERPOWERS # OVERPOWERED # TRANSMIGRATION # CULTIVATION",
      "genres": [
        "Web Novel"
      ],
      "metadata": {
        "ranking_page": "https://www.webnovel.com/ranking/novel/season/best_sellers"
      },
      "previous_score": 13.0,
      "velocity": -0.07692307692307693
    },
    {
      "id": "webnovel-book-global-deities-rising-as-wood-elves'-god_35234032408256805",
      "title": "Global Deities: Rising as Wood Elves' God",
      "source": "WebNovel",
      "category": "web_novel",
      "score": 10.0,
      "url": "https://www.webnovel.com/book/global-deities-rising-as-wood-elves'-god_35234032408256805",
      "image": "https://book-pic.webnovel.com/bookcover/35234032408256805?imageMogr2/thumbnail/600x&imageId=1777342792009",
      "description": "# SYSTEM # WEAKTOSTRONG # KINGDOMBUILDING",
      "genres": [
        "Web Novel"
      ],
      "metadata": {
        "ranking_page": "https://www.webnovel.com/ranking/novel/season/best_sellers"
      },
      "previous_score": 11.0,
      "velocity": -0.09090909090909091
    },
    {
      "id": "goodnovel-book-Ex-Husband-s-Regret_31000657155",
      "title": "Ex-Husband's Regret",
      "source": "GoodNovel",
      "category": "romance",
      "score": 11.0,
      "url": "https://www.goodnovel.com/book/Ex-Husband-s-Regret_31000657155",
      "image": "https://acf.goodnovel.com/book/202309/Ex-Husband-s-Regret/f7c3f3b5a311ea1b6324681fe244b3576ab84ba66839667827ebd33e879a567e.jpg?v=1&p=1&w=1080&a=webp",
      "description": "Ava: Nine years ago I did something terrible. it wasn't one of my best moments but I saw an opportunity to have the guy I've loved since I was a young girl and I took it. Fast forward to years later and I'm tired of living in a loveless marriage. I want to free both of us from a marriage that should never have taken place. They say if you love something.... It was time to let him go. I know he'll never love me and that I'll never be his choice. His heart will always belong to Her and despite my sins, I deserve to be loved.Rowan: Nine years ago, I was so in love I could barely see right. I ruined it when I made the worst mistake of my life and in the process I lost the love of my life. I knew I had to step up in my responsibility and so I did, with an unwanted wife. With the wrong woman. Now she has once again flipped my life by divorcing me. To make matters even more complicated, the love of my life is back in town. Now the only question is, who is the right woman? Is it the girl I fell head over heels in love with years ago? or is it my ex wife, the woman I never wanted but had to marry?",
      "genres": [
        "Romance"
      ],
      "metadata": {
        "ranking_page": "https://www.goodnovel.com/"
      },
      "previous_score": 13.0,
      "velocity": -0.15384615384615385
    },
    {
      "id": "webnovel-book-rebate-king-every-beauty-i-spoil-makes-me-a-billionaire_35492500200946605",
      "title": "Rebate King: Every Beauty I Spoil Makes Me a Billionaire",
      "source": "WebNovel",
      "category": "web_novel",
      "score": 5.0,
      "url": "https://www.webnovel.com/book/rebate-king-every-beauty-i-spoil-makes-me-a-billionaire_35492500200946605",
      "image": "https://book-pic.webnovel.com/bookcover/35492500200946605?imageMogr2/thumbnail/600x&imageId=1779867926769",
      "description": "# ROMANCE # SYSTEM # R18 # HAREM # SLICEOFLIFE # GENIUS # SMUT # CAMPUS # URBAN # FACESLAPPING",
      "genres": [
        "Web Novel"
      ],
      "metadata": {
        "ranking_page": "https://www.webnovel.com/ranking/novel/season/best_sellers"
      },
      "previous_score": 7.0,
      "velocity": -0.2857142857142857
    },
    {
      "id": "webnovel-book-infinite-cashback-system_35674644400458505",
      "title": "Infinite Cashback System",
      "source": "WebNovel",
      "category": "web_novel",
      "score": 4.0,
      "url": "https://www.webnovel.com/book/infinite-cashback-system_35674644400458505",
      "image": "https://book-pic.webnovel.com/bookcover/35674644400458505?imageMogr2/thumbnail/600x&imageId=1780250189855",
      "description": "# ROMANCE # ADVENTURE # R18 # HAREM # SLICEOFLIFE # CAMPUS # ACADEMY # URBAN # CEO # POORTORICH",
      "genres": [
        "Web Novel"
      ],
      "metadata": {
        "ranking_page": "https://www.webnovel.com/ranking/novel/season/best_sellers"
      },
      "previous_score": 6.0,
      "velocity": -0.3333333333333333
    },
    {
      "id": "webnovel-book-reborn-with-a-space-hoarding-food-and-raising-my-kid_35479981200689605",
      "title": "Reborn with a Space: Hoarding Food and Raising My Kid",
      "source": "WebNovel",
      "category": "web_novel",
      "score": 3.0,
      "url": "https://www.webnovel.com/book/reborn-with-a-space-hoarding-food-and-raising-my-kid_35479981200689605",
      "image": "https://book-pic.webnovel.com/bookcover/35479981200689605?imageMogr2/thumbnail/600x&imageId=1778213367628",
      "description": "# WEAKTOSTRONG # APOCALYPSE # REBIRTH # HEALING # FARMING # STORAGESPACE",
      "genres": [
        "Web Novel"
      ],
      "metadata": {
        "ranking_page": "https://www.webnovel.com/ranking/novel/season/best_sellers"
      },
      "previous_score": 8.0,
      "velocity": -0.625
    },
    {
      "id": "webnovel-book-infinite-evolution-dominating-the-apocalypse-with-my-god-tier-items_35460563000367305",
      "title": "Infinite Evolution: Dominating The Apocalypse With My God Tier Items",
      "source": "WebNovel",
      "category": "web_novel",
      "score": 2.0,
      "url": "https://www.webnovel.com/book/infinite-evolution-dominating-the-apocalypse-with-my-god-tier-items_35460563000367305",
      "image": "https://book-pic.webnovel.com/bookcover/35460563000367305?imageMogr2/thumbnail/600x&imageId=1778661436014",
      "description": "# ACTION # ROMANCE # ADVENTURE # SYSTEM # DARK # SUPERPOWERS # OVERPOWERED # SURVIVAL # APOCALYPSE # GENES",
      "genres": [
        "Web Novel"
      ],
      "metadata": {
        "ranking_page": "https://www.webnovel.com/ranking/novel/season/best_sellers"
      },
      "previous_score": 9.0,
      "velocity": -0.7777777777777778
    },
    {
      "id": "anilist-manga-74347",
      "title": "One-Punch Man",
      "source": "AniList",
      "category": "manga",
      "score": 169523.0,
      "url": "https://anilist.co/manga/74347",
      "image": "https://s4.anilist.co/file/anilistcdn/media/manga/cover/large/bx74347-sZpmNJ5xLwRK.jpg",
      "description": "In this new action-comedy, everything about a young man named Saitama screams \"AVERAGE,&rdquo; from his lifeless expression, to his bald head, to his unimpressive physique. However, this average-looking fellow doesn't have your average problem... He's actually a superhero that's looking for tough opponents! The problem is, every time he finds a promising candidate he beats the snot out of them in one punch. Can Saitama finally find an evil villain strong enough to challenge him? Follow Saitama through his hilarious romps as he searches for new bad guys to challenge!\n<br><br>\n(Source: VIZ Media)",
      "genres": [
        "Action",
        "Comedy",
        "Sci-Fi",
        "Supernatural"
      ],
      "metadata": {
        "average_score": 85,
        "country_of_origin": "JP",
        "format": "MANGA"
      },
      "previous_score": null,
      "velocity": null
    },
    {
      "id": "anilist-manga-46765",
      "title": "Kingdom",
      "source": "AniList",
      "category": "manga",
      "score": 73758.0,
      "url": "https://anilist.co/manga/46765",
      "image": "https://s4.anilist.co/file/anilistcdn/media/manga/cover/large/nx46765-KPXir4sRqJBW.png",
      "description": "Xin is a war orphan in a poor village in the kingdom of Qin. He has big dreams of becoming a great general, and when his best friend’s life is cut short by political machinations, Xin sets off to find a deposed ruler and help restore his place on the throne, while working his way up through the ranks of the Qin kingdom’s army to do what no one has ever done before—unify China.\n<br><br>\n(Source: VIZ Media)",
      "genres": [
        "Action",
        "Drama"
      ],
      "metadata": {
        "average_score": 89,
        "country_of_origin": "JP",
        "format": "MANGA"
      },
      "previous_score": null,
      "velocity": null
    },
    {
      "id": "anilist-anime-199588",
      "title": "Gals Can't Be Kind to Otaku!?",
      "source": "AniList",
      "category": "anime",
      "score": 54101.0,
      "url": "https://anilist.co/anime/199588",
      "image": "https://s4.anilist.co/file/anilistcdn/media/anime/cover/large/bx199588-M2vtWicvqNbU.jpg",
      "description": "Meet Takuya Seo, an otaku who sits behind the popular gals in class, Ijichi and Amane. Since they're people from different \"castes,\" you wouldn't expect them to have much in common. But when their worlds collide over a borrowed eraser, Takuya slips up about his favorite anime, and Amane...is rather quick to correct him. She says she's not a fan, but her familiarity with the series suggests otherwise. Could she be...a fellow geek?!\n<br><br>\n(Source: Yen Press)",
      "genres": [
        "Comedy",
        "Romance"
      ],
      "metadata": {
        "average_score": 76
      },
      "previous_score": null,
      "velocity": null
    },
    {
      "id": "anilist-manga-120980",
      "title": "Nano Machine",
      "source": "AniList",
      "category": "manhwa",
      "score": 45041.0,
      "url": "https://anilist.co/manga/120980",
      "image": "https://s4.anilist.co/file/anilistcdn/media/manga/cover/large/bx120980-RZ9WLd0o9hyo.jpg",
      "description": "Nanotechnology meets martial arts at the Mashin Academy. Yeo-Un’s mother may not be one of the High Priest’s six official wives, but his father’s blood still qualifies him for a chance at the position of Minor Priest. Will a mysterious nanomachine injection from a future descendent help Yeo-un in this fierce competition against his powerful half-siblings?\n<br><br>\n(Source: WEBTOON)\n",
      "genres": [
        "Action",
        "Adventure",
        "Fantasy",
        "Sci-Fi"
      ],
      "metadata": {
        "average_score": 81,
        "country_of_origin": "KR",
        "format": "MANGA"
      },
      "previous_score": null,
      "velocity": null
    },
    {
      "id": "anilist-manga-144957",
      "title": "The World After the Fall",
      "source": "AniList",
      "category": "manhwa",
      "score": 41946.0,
      "url": "https://anilist.co/manga/144957",
      "image": "https://s4.anilist.co/file/anilistcdn/media/manga/cover/large/bx144957-h0qIwRwxOEdg.jpg",
      "description": "Faced with imminent defeat and certain death, would you choose to run – or continue to fight for a doomed world? When mysterious towers appear across the world, summoning monsters that prey on mankind, this is the choice presented to the Tower Walkers – adventurers with special powers to fight the monsters. On the brink of death, they can choose to use a “regression stone” to return to the past for a second chance, though this decision places them in a separate timeline forever. Stubborn Tower Walker Jae-Hwan rejects this choice, choosing to fight for the original timeline, and learning shocking secrets about the Tower along the way.<br>\n<br>\n(Source: WEBTOON, edited)",
      "genres": [
        "Action",
        "Adventure",
        "Fantasy"
      ],
      "metadata": {
        "average_score": 76,
        "country_of_origin": "KR",
        "format": "MANGA"
      },
      "previous_score": null,
      "velocity": null
    },
    {
      "id": "anilist-manga-159441",
      "title": "Pick Me Up",
      "source": "AniList",
      "category": "manhwa",
      "score": 40401.0,
      "url": "https://anilist.co/manga/159441",
      "image": "https://s4.anilist.co/file/anilistcdn/media/manga/cover/large/bx159441-9W8201jAT9Yv.jpg",
      "description": "1-Star heroes are just fodder for learning a boss' attack patterns. That was Seojin Han's philosophy when playing the notoriously difficult game Pick Me Up. But after being transported into the game as one of those 1-star heroes, he's got no choice but to rise in rank and defeat the player controlling him and his party. Can a gacha game character hope to defeat a player akin to being his god?\n<br><br>(Source: Tapas)",
      "genres": [
        "Action",
        "Adventure",
        "Fantasy"
      ],
      "metadata": {
        "average_score": 84,
        "country_of_origin": "KR",
        "format": "MANGA"
      },
      "previous_score": null,
      "velocity": null
    },
    {
      "id": "anilist-manga-138072",
      "title": "JoJo no Kimyou na Bouken: The JOJOLands",
      "source": "AniList",
      "category": "manga",
      "score": 28126.0,
      "url": "https://anilist.co/manga/138072",
      "image": "https://s4.anilist.co/file/anilistcdn/media/manga/cover/large/bx138072-G9PrTnqb8CRI.jpg",
      "description": "The stage is set on a volcanic island in the Pacific Ocean, Hawaii. Jodio Joestar, a young boy living on Oahu Island, harbors the ambition to become a great millionaire. The clue to his goal lies in reaching the pinnacle of the mechanisms of this world. What means will he choose to achieve his objective?",
      "genres": [
        "Action",
        "Adventure",
        "Supernatural"
      ],
      "metadata": {
        "average_score": 82,
        "country_of_origin": "JP",
        "format": "MANGA"
      },
      "previous_score": null,
      "velocity": null
    },
    {
      "id": "anilist-anime-180228",
      "title": "Go For It, Nakamura-kun!!",
      "source": "AniList",
      "category": "anime",
      "score": 26639.0,
      "url": "https://anilist.co/anime/180228",
      "image": "https://s4.anilist.co/file/anilistcdn/media/anime/cover/large/bx180228-MuZ7adbGiYVj.jpg",
      "description": "Love at first sight is no myth—just ask Okuto Nakamura. Whenever his dreamy classmate Aiki Hirose enters the room, his heart skips a beat, despite the fact that they’ve never actually spoken. Not to mention, Nakamura is a complete klutz with zero friends. Will he ruin his chance at love before it even begins?\n<br><br>\n(Source: Crunchyroll)\n<br><br>\n<i>Note: The series streamed a week in advance on Hulu Japan starting with episode 2 released alongside episode 1.</i>",
      "genres": [
        "Comedy",
        "Romance",
        "Slice of Life"
      ],
      "metadata": {
        "average_score": 78
      },
      "previous_score": null,
      "velocity": null
    },
    {
      "id": "anilist-anime-199029",
      "title": "Rent-a-Girlfriend Season 5",
      "source": "AniList",
      "category": "anime",
      "score": 18327.0,
      "url": "https://anilist.co/anime/199029",
      "image": "https://s4.anilist.co/file/anilistcdn/media/anime/cover/large/bx199029-8eMkhHlD62Ik.png",
      "description": "The fifth season of <i>Kanojo, Okarishimasu</i>.\n<br><br>\n<i>Note: Kanojo, Okarishimasu 5th Season was streamed 2 days in advance of the TV broadcast on DMM TV beginning April 8, 2026. Regular broadcasting began on April 11, 2026.</i>",
      "genres": [
        "Comedy",
        "Romance"
      ],
      "metadata": {
        "average_score": 57
      },
      "previous_score": null,
      "velocity": null
    },
    {
      "id": "anilist-anime-201817",
      "title": "Always a Catch!",
      "source": "AniList",
      "category": "anime",
      "score": 17785.0,
      "url": "https://anilist.co/anime/201817",
      "image": "https://s4.anilist.co/file/anilistcdn/media/anime/cover/large/bx201817-pyfL9F8muPeq.jpg",
      "description": "Born into a legendary ducal family, martial prodigy Maria “Mimi” Annovazzi loses her claim as heir and is suddenly ordered to marry into prestige. With no options left in her homeland, she transfers to a neighboring kingdom—only to be publicly dumped at graduation by a prince she’s never met over an engagement she didn’t even know she had! Will Maria be doomed to the life of a spinster?!<Br><br>(Source: Crunchyroll)",
      "genres": [
        "Comedy",
        "Fantasy",
        "Romance"
      ],
      "metadata": {
        "average_score": 70
      },
      "previous_score": null,
      "velocity": null
    },
    {
      "id": "anilist-anime-198939",
      "title": "Reborn as a Vending Machine, I Now Wander the Dungeon Season 3",
      "source": "AniList",
      "category": "anime",
      "score": 13071.0,
      "url": "https://anilist.co/anime/198939",
      "image": "https://s4.anilist.co/file/anilistcdn/media/anime/cover/large/bx198939-95aqzBr0Lzcv.jpg",
      "description": "The third season of <i>Jidou Hanbaiki ni Umarekawatta Ore wa Meikyuu wo Samayou.</i>",
      "genres": [
        "Action",
        "Comedy",
        "Fantasy"
      ],
      "metadata": {
        "average_score": 64
      },
      "previous_score": null,
      "velocity": null
    },
    {
      "id": "anilist-manga-201773",
      "title": "Haimiya Is Scary Cute",
      "source": "AniList",
      "category": "manga",
      "score": 12473.0,
      "url": "https://anilist.co/manga/201773",
      "image": "https://s4.anilist.co/file/anilistcdn/media/manga/cover/large/bx201773-ecGmhCRhfu05.jpg",
      "description": "At my high school, everyone fears Haimiya-senpai. With her sharp piercings, striking grey wolf-cut, and that brutally honest Kansai dialect, she has a reputation for being downright terrifying. Yet, for some mysterious reason...this intimidating upperclassman is kind and gentle only to me! The curtain rises upon this heart-fluttering romantic comedy about a terrifying-yet-sweet senpai!\n<BR><BR>\n(Source: Manga UP!)",
      "genres": [
        "Comedy",
        "Romance",
        "Slice of Life"
      ],
      "metadata": {
        "average_score": 79,
        "country_of_origin": "JP",
        "format": "MANGA"
      },
      "previous_score": null,
      "velocity": null
    },
    {
      "id": "anilist-manga-184502",
      "title": "The Academy’s Sashimi Sword Master",
      "source": "AniList",
      "category": "manhwa",
      "score": 12267.0,
      "url": "https://anilist.co/manga/184502",
      "image": "https://s4.anilist.co/file/anilistcdn/media/manga/cover/large/bx184502-uu4QoBUwEfNH.jpg",
      "description": "Chef Kim, Korea's legendary sashimi master, is transported into the world of Blessing M, a mobile game he once played. But instead of being a hero, he finds himself as Geomma Kang, a mere background extra. Forced into a new life, Geomma discovers a new power: the Blessing of the Blade God. Now, to survive in this game-like world, he must slice through challenges and enemies alike. Will his unmatched skills in the kitchen be enough to carve out a new destiny?\n<br><br>\n(Source: WEBTOON)",
      "genres": [
        "Action",
        "Fantasy"
      ],
      "metadata": {
        "average_score": 74,
        "country_of_origin": "KR",
        "format": "MANGA"
      },
      "previous_score": null,
      "velocity": null
    },
    {
      "id": "anilist-manga-199999",
      "title": "WITCHRIV",
      "source": "AniList",
      "category": "manga",
      "score": 6285.0,
      "url": "https://anilist.co/manga/199999",
      "image": "https://s4.anilist.co/file/anilistcdn/media/manga/cover/large/bx199999-O8TW8Ufc3sXv.png",
      "description": "A girl named Nona lives in plain sight among humans, hiding her true identity as a mage as she spends her days in peace with her best friend Lovi. But one day, Nona uses magic to fix Lovi's glasses and subsequently catches the attention of the Bureau of Magic Surveillance. A simple good deed becomes the trigger that sets Nona's destiny in motion...\n<br><br>\n(Source: MANGA Plus)",
      "genres": [
        "Drama",
        "Fantasy",
        "Mystery"
      ],
      "metadata": {
        "average_score": 72,
        "country_of_origin": "JP",
        "format": "MANGA"
      },
      "previous_score": null,
      "velocity": null
    },
    {
      "id": "anilist-manga-185816",
      "title": "The Heavenly Demon Wants a Quiet Life",
      "source": "AniList",
      "category": "manhwa",
      "score": 5460.0,
      "url": "https://anilist.co/manga/185816",
      "image": "https://s4.anilist.co/file/anilistcdn/media/manga/cover/large/bx185816-DhnjJEpwiur1.jpg",
      "description": "After a lifetime of bloodshed, the Heavenly Demon longs for peace. In his final moments, he uncovers the truth about his power and yearns for a different life. He wakes up in the body of Tae-San Byeok, the frail second son of a powerful merchant family, barely clinging to life. Using his knowledge from his life as the Heavenly Demon, Tae-San must navigate a world of temptation and corruption to survive. As his martial arts reputation grows, new enemies emerge to disrupt his quiet life. Yet, Tae-San is determined to live on his own terms, despite the chaos around him.<br><br>(Source: WEBTOON)",
      "genres": [
        "Action",
        "Adventure",
        "Fantasy"
      ],
      "metadata": {
        "average_score": 70,
        "country_of_origin": "KR",
        "format": "MANGA"
      },
      "previous_score": null,
      "velocity": null
    },
    {
      "id": "anilist-manga-195083",
      "title": "We're J-Just Childhood Friends",
      "source": "AniList",
      "category": "manga",
      "score": 3522.0,
      "url": "https://anilist.co/manga/195083",
      "image": "https://s4.anilist.co/file/anilistcdn/media/manga/cover/large/bx195083-hN45rN4kxdTi.jpg",
      "description": "Yuichi and Sumi were childhood friends who were always together. However, as they grew up, they drifted apart, but a chance encounter brings them back into each other’s lives…\n<br><br>\n(Source: Manga Plus)",
      "genres": [
        "Comedy",
        "Romance"
      ],
      "metadata": {
        "average_score": 71,
        "country_of_origin": "JP",
        "format": "MANGA"
      },
      "previous_score": null,
      "velocity": null
    },
    {
      "id": "anilist-manga-202332",
      "title": "Yotaka Futatabi",
      "source": "AniList",
      "category": "manga",
      "score": 3063.0,
      "url": "https://anilist.co/manga/202332",
      "image": "https://s4.anilist.co/file/anilistcdn/media/manga/cover/large/bx202332-pWJdpDEKY8KP.jpg",
      "description": "That woman is \"Yotaka.\" Once famous in the underworld as the strongest assassin, she is now a 33-year-old (and very unlucky) drug addict and alcoholic. She's enjoying her unemployed life in a rundown apartment. ♪ With her mind and body completely slack, Yotaka receives an invitation from her assassin friend, \"Kohai,\" to return to active duty...!!<br><br>\nWill she return to the battlefield once again?! Yotaka!!!<br><br>(Source: Kodansha, translated)",
      "genres": [
        "Action",
        "Comedy",
        "Ecchi"
      ],
      "metadata": {
        "average_score": 67,
        "country_of_origin": "JP",
        "format": "MANGA"
      },
      "previous_score": null,
      "velocity": null
    },
    {
      "id": "goodnovel-book-Once-a-Doormat-Now-Untouchable_31001082710",
      "title": "Once a Doormat, Now Untouchable",
      "source": "GoodNovel",
      "category": "romance",
      "score": 15.0,
      "url": "https://www.goodnovel.com/book/Once-a-Doormat-Now-Untouchable_31001082710",
      "image": "https://acf.goodnovel.com/book/202510/a502e1638708ce908ddec7d4bb8383b442ed50efa99638db63fe56e7ceccf9a9.jpg?v=1&p=1&w=1080&a=webp",
      "description": "Three years into her marriage to Caleb Hampton, Sydney Wilson finally learned the truth: the woman he loved was his sister-in-law.\nOn the night his brother died, Sydney saw Caleb's true nature. At the funeral, she did not even flinch when Caleb took a slap meant for his sister-in-law.\nShe always knew he had married her because she was quiet, obedient, and easy to control. She proved it, even in the way she left him.\nNo dramatic fights. No tearful confrontations. Just a divorce quietly signed, sealed, and hidden.\nWhat Caleb didn't know was that they were already divorced. Sydney had stopped being quiet and was already seeing someone else.\nThe day Sydney's breakthrough cancer drug took the world by storm, she received accolades and glory.\nEveryone cheered—except Caleb, who dropped to one knee, his eyes bloodshot with desperation, begging for a second chance.\nBut a possessive arm wrapped around Sydney's waist, declaring to the world, \"Sorry, but she's getting married. To me.\"",
      "genres": [
        "Romance"
      ],
      "metadata": {
        "ranking_page": "https://www.goodnovel.com/"
      },
      "previous_score": null,
      "velocity": null
    },
    {
      "id": "goodnovel-book-My-Alpha-Stepbrother-s-Dirty-Secret_31001226188",
      "title": "My Alpha Stepbrother's Dirty Secret",
      "source": "GoodNovel",
      "category": "romance",
      "score": 14.0,
      "url": "https://www.goodnovel.com/book/My-Alpha-Stepbrother-s-Dirty-Secret_31001226188",
      "image": "https://acf.goodnovel.com/book/202507/64a74832dde8868d85a5a4a04f6ddc8f912be50627bcee87d74021b9c9759c13.jpg?v=1&p=1&w=1080&a=webp",
      "description": "🔥 THIS STORY CONTAINS EXPLICIT SEX SCENES, POSSESSIVE ALPHA ENERGY, AND INTENSE EMOTIONAL TENSION. READER DISCRETION IS STRONGLY ADVISED.\r\n\r\n\r\nWhen Liana Rivers fell into bed with her brooding, dominant, dangerously irresistible stepbrother, Killian Wolfe, she gave him everything, her heart, her body, her virginity.\r\n\r\nBut when she discovered she was pregnant and found out he was engaged to another woman, she ran quietly, carrying a shattered heart and a baby he would never know.\r\n\r\nNow, seven years later, she’s a struggling single mom working as a hotel janitor, doing everything she can to hide her past, and her son from the ruthless Alpha who broke her. Until one night, he finds her again. Richer. Darker. More powerful than ever. And he wants her back.\r\n\r\nKillian isn’t just here to play house. He wants control. Of her life. Her body. Her son. And this time, he's not asking.\r\n\r\nShe ran from him once. But now that he knows the truth… He’ll burn the whole damn world to keep what’s his.",
      "genres": [
        "Romance"
      ],
      "metadata": {
        "ranking_page": "https://www.goodnovel.com/"
      },
      "previous_score": null,
      "velocity": null
    },
    {
      "id": "goodnovel-book-The-Endgame-Chronicles_31001107239",
      "title": "The Endgame Chronicles",
      "source": "GoodNovel",
      "category": "romance",
      "score": 13.0,
      "url": "https://www.goodnovel.com/book/The-Endgame-Chronicles_31001107239",
      "image": "https://acf.goodnovel.com/book/202601/7e451817822952f4edeaab07a0efb482a24fb67c60657abe16198bda4a5d2a92.jpg?v=1&p=1&w=1080&a=webp",
      "description": "After surviving the brutal apocalypse for ten years, hardened survivor Hayley Reid was betrayed by her base and unexpectedly woke up two weeks before the apocalypse began.\n\nBack in time, her useless father and stepmother were still pressuring her to give up her house for her brother and his newlywed wife. This time, Hayley didn’t hesitate to sell them the house for dirt cheap.\n\nWhile they celebrate this great deal, Hayley went crazy stockpiling supplies. With the help of the super base system’s overpowered perks, she built an unbeatable shelter.\n\nWhile everyone else was stuck in zombie chaos, Hayley relaxed in her fortress like she was on vacation.\n\nWhile everyone else struggled to find food, her dog enjoyed a full buffet every day.\n\nWhile everyone else risked their lives squeezing into crowded survivor camps, Hayley’s base stood as the strongest steel fortress in the whole world!",
      "genres": [
        "Romance"
      ],
      "metadata": {
        "ranking_page": "https://www.goodnovel.com/"
      },
      "previous_score": null,
      "velocity": null
    },
    {
      "id": "goodnovel-book-Reclaimed-by-My-Alpha_31001020267",
      "title": "Reclaimed by My Alpha",
      "source": "GoodNovel",
      "category": "romance",
      "score": 12.0,
      "url": "https://www.goodnovel.com/book/Reclaimed-by-My-Alpha_31001020267",
      "image": "https://acf.goodnovel.com/book/202505/3daa21c69376f8dd6e65df14de8716179c5e8657785ae21179c5df7c6b56ad40.jpg?v=1&p=1&w=1080&a=webp",
      "description": "Natalia and Andrei’s marriage was originally a three-year contract. With only 30 days left until the contract ends, Natalia discovered that she’s pregnant. \nJust when she thought Andrei would reconsider divorcing her because of this, his deceased first mate, Lilith, returned. Feeling hopeless, Natalia decided to initiate the divorce. \nHowever, at their engagement party, Andrei received the news of Natalia’s car accident, along with the shocking discovery of her pregnancy test results...",
      "genres": [
        "Romance"
      ],
      "metadata": {
        "ranking_page": "https://www.goodnovel.com/"
      },
      "previous_score": null,
      "velocity": null
    },
    {
      "id": "goodnovel-book-Alpha-s-Second-Chance_31000715956",
      "title": "Alpha's Second Chance",
      "source": "GoodNovel",
      "category": "romance",
      "score": 2.0,
      "url": "https://www.goodnovel.com/book/Alpha-s-Second-Chance_31000715956",
      "image": "https://acf.goodnovel.com/book/202529/141c8653b9cb549ac72fa248d218946cdde6aae7fa0366fecc9c2cb28a318861.jpg?v=1&p=1&w=1080&a=webp",
      "description": "Alpha's Second Chance is a Werewolf novel written by Salani that covers Second Chance, Betrayal, Rogue. Read full chapters of this story online on GoodNovel.",
      "genres": [
        "Romance"
      ],
      "metadata": {
        "ranking_page": "https://www.goodnovel.com/"
      },
      "previous_score": null,
      "velocity": null
    }
  ]
}